[{"pos":"QB","name":"Joe Burrow","school":"LSU","conf":"SEC","cfr_id":"joe-burrow-1","pfr_id":"BurrJo01","age":23.4055,"round":1.0,"overall":1.0,"years":4,"markers":14,"adjMarkers":17.0,"grade":88.8889,"ath":0.0,"prod":0.9333,"pff":8.0,"lastPPG":35.3493,"bestPPG":35.3493,"wt":221.0,"ht":75.0,"bmi":27.6229,"careerPA":945.0,"careerCMP":0.6878,"careerPYd":8852.0,"careerPTD":78.0,"careerINT":11.0,"careerPAPG":24.2308,"careerYPA":9.3672,"careerYPG":226.9744,"careerTDPG":2.0,"careerINTPG":0.2821,"careerRuYd":820.0,"careerRuYPG":21.0256,"bestPYd":5671.0,"bestPTD":60.0,"bestINT":5.0,"bestCMP":0.763,"bestRuYd":399.0,"careerAcc":0.7754,"careerBTT":0.07,"careerTWP":0.0361,"careerSackPct":0.0676,"bestAcc":0.819,"bestBTT":0.075,"bestTWP":0.018,"bestSackPct":0.059,"rank":null},{"pos":"QB","name":"Tua Tagovailoa","school":"Alabama","conf":"SEC","cfr_id":"tua-tagovailoa-1","pfr_id":"TagoTu00","age":22.1808,"round":1.0,"overall":5.0,"years":3,"markers":13,"adjMarkers":16.0,"grade":85.1852,"ath":0.5,"prod":0.8667,"pff":9.0,"lastPPG":28.4778,"bestPPG":28.4778,"wt":217.0,"ht":73.0,"bmi":28.6294,"careerPA":684.0,"careerCMP":0.693,"careerPYd":7442.0,"careerPTD":87.0,"careerINT":11.0,"careerPAPG":20.7273,"careerYPA":10.8801,"careerYPG":225.5152,"careerTDPG":2.6364,"careerINTPG":0.3333,"careerRuYd":340.0,"careerRuYPG":10.303,"bestPYd":3966.0,"bestPTD":43.0,"bestINT":3.0,"bestCMP":0.714,"bestRuYd":190.0,"careerAcc":0.7761,"careerBTT":0.0743,"careerTWP":0.035,"careerSackPct":0.0305,"bestAcc":0.79,"bestBTT":0.087,"bestTWP":0.0218,"bestSackPct":0.026,"rank":null},{"pos":"QB","name":"Justin Herbert","school":"Oregon","conf":"Pac-12","cfr_id":"justin-herbert-1","pfr_id":"HerbJu00","age":22.1589,"round":1.0,"overall":6.0,"years":4,"markers":9,"adjMarkers":12.0,"grade":70.3704,"ath":0.5,"prod":0.5333,"pff":9.0,"lastPPG":20.7029,"bestPPG":22.8275,"wt":236.0,"ht":78.0,"bmi":27.2723,"dash":4.68,"wass":98.3917,"burst":121.85,"careerPA":1293.0,"careerCMP":0.6396,"careerPYd":10541.0,"careerPTD":95.0,"careerINT":23.0,"careerPAPG":29.3864,"careerYPA":8.1524,"careerYPG":239.5682,"careerTDPG":2.1591,"careerINTPG":0.5227,"careerRuYd":560.0,"careerRuYPG":12.7273,"bestPYd":3471.0,"bestPTD":32.0,"bestINT":4.0,"bestCMP":0.675,"bestRuYd":183.0,"careerAcc":0.7428,"careerBTT":0.0653,"careerTWP":0.0361,"careerSackPct":0.048,"bestAcc":0.775,"bestBTT":0.092,"bestTWP":0.0216,"bestSackPct":0.043,"rank":null},{"pos":"QB","name":"Jalen Hurts","school":"Oklahoma","conf":"Big 12","cfr_id":"jalen-hurts-1","pfr_id":"HurtJa00","age":21.663,"round":2.0,"overall":53.0,"years":4,"markers":12,"adjMarkers":11.0,"grade":66.6667,"ath":0.5,"prod":0.7333,"pff":5.0,"lastPPG":38.1671,"bestPPG":38.1671,"wt":222.0,"ht":73.0,"bmi":29.2891,"dash":4.59,"wass":100.0305,"burst":122.0,"careerPA":1046.0,"careerCMP":0.652,"careerPYd":9477.0,"careerPTD":80.0,"careerINT":20.0,"careerPAPG":18.6786,"careerYPA":9.0602,"careerYPG":169.2321,"careerTDPG":1.4286,"careerINTPG":0.3571,"careerRuYd":3274.0,"careerRuYPG":58.4643,"bestPYd":3851.0,"bestPTD":32.0,"bestINT":1.0,"bestCMP":0.697,"bestRuYd":1298.0,"careerAcc":0.7652,"careerBTT":0.0495,"careerTWP":0.0333,"careerSackPct":0.0584,"bestAcc":0.769,"bestBTT":0.051,"bestTWP":0.0211,"bestSackPct":0.05,"rank":null},{"pos":"QB","name":"Jordan Love","school":"Utah State","conf":"MWC","cfr_id":"jordan-love-2","pfr_id":"LoveJo03","age":21.5096,"round":1.0,"overall":26.0,"years":3,"markers":7,"adjMarkers":8.0,"grade":55.5556,"ath":0.5,"prod":0.4,"pff":6.0,"lastPPG":16.66,"bestPPG":24.0754,"wt":224.0,"ht":76.0,"bmi":27.2659,"dash":4.74,"wass":88.7492,"burst":119.35,"careerPA":1125.0,"careerCMP":0.6124,"careerPYd":8600.0,"careerPTD":60.0,"careerINT":29.0,"careerPAPG":29.6053,"careerYPA":7.6444,"careerYPG":226.3158,"careerTDPG":1.5789,"careerINTPG":0.7632,"careerRuYd":403.0,"careerRuYPG":10.6053,"bestPYd":3567.0,"bestPTD":32.0,"bestINT":6.0,"bestCMP":0.64,"bestRuYd":175.0,"careerAcc":0.7094,"careerBTT":0.054,"careerTWP":0.0434,"careerSackPct":0.0314,"bestAcc":0.727,"bestBTT":0.064,"bestTWP":0.032,"bestSackPct":0.021,"rank":null},{"pos":"QB","name":"Nathan Rourke","school":"Ohio","conf":"MAC","cfr_id":"nathan-rourke-1","age":21.9534,"round":8.0,"years":3,"markers":6,"adjMarkers":2.0,"grade":37.5,"ath":0.0,"prod":0.4,"pff":5.0,"lastPPG":27.6692,"bestPPG":28.9323,"careerPA":895.0,"careerCMP":0.5877,"careerPYd":7454.0,"careerPTD":60.0,"careerINT":20.0,"careerPAPG":22.9487,"careerYPA":8.3285,"careerYPG":191.1282,"careerTDPG":1.5385,"careerINTPG":0.5128,"careerRuYd":2639.0,"careerRuYPG":67.6667,"bestPYd":2820.0,"bestPTD":23.0,"bestINT":5.0,"bestCMP":0.61,"bestRuYd":912.0,"careerAcc":0.6883,"careerBTT":0.0749,"careerTWP":0.0547,"careerSackPct":0.0548,"bestAcc":0.701,"bestBTT":0.085,"bestTWP":0.0385,"bestSackPct":0.05,"rank":null},{"pos":"QB","name":"Tyler Huntley","school":"Utah","conf":"Pac-12","cfr_id":"tyler-huntley-1","pfr_id":"HuntTy01","age":22.2548,"round":8.0,"years":4,"markers":6,"adjMarkers":2.0,"grade":37.5,"ath":0.0,"prod":0.4,"pff":4.0,"lastPPG":18.1914,"bestPPG":23.614,"careerPA":854.0,"careerCMP":0.6721,"careerPYd":7351.0,"careerPTD":46.0,"careerINT":20.0,"careerPAPG":23.0811,"careerYPA":8.6077,"careerYPG":198.6757,"careerTDPG":1.2432,"careerINTPG":0.5405,"careerRuYd":1146.0,"careerRuYPG":30.973,"bestPYd":3092.0,"bestPTD":19.0,"bestINT":4.0,"bestCMP":0.731,"bestRuYd":537.0,"careerAcc":0.779,"careerBTT":0.0492,"careerTWP":0.034,"careerSackPct":0.0805,"bestAcc":0.826,"bestBTT":0.057,"bestTWP":0.0162,"bestSackPct":0.068,"rank":null},{"pos":"QB","name":"Anthony Gordon","school":"Washington State","conf":"Pac-12","cfr_id":"anthony-gordon-2","age":23.6877,"round":8.0,"years":2,"markers":6,"adjMarkers":2.0,"grade":34.6154,"ath":0.0,"prod":0.4,"pff":5.0,"lastPPG":30.5508,"bestPPG":30.5508,"wt":205.0,"ht":74.0,"bmi":26.3202,"careerPA":694.0,"careerCMP":0.7147,"careerPYd":5596.0,"careerPTD":48.0,"careerINT":17.0,"careerPAPG":43.375,"careerYPA":8.0634,"careerYPG":349.75,"careerTDPG":3.0,"careerINTPG":1.0625,"careerRuYd":-20.0,"careerRuYPG":-1.25,"bestPYd":5579.0,"bestPTD":48.0,"bestINT":16.0,"bestCMP":0.716,"bestRuYd":0.0,"careerAcc":0.7969,"careerBTT":0.0402,"careerTWP":0.0402,"careerSackPct":0.0268,"bestAcc":0.798,"bestBTT":0.039,"bestTWP":0.0365,"bestSackPct":0.027,"rank":null},{"pos":"QB","name":"Steven Montez","school":"Colorado","conf":"Pac-12","cfr_id":"steven-montez-1","age":23.3096,"round":8.0,"years":4,"markers":6,"adjMarkers":2.0,"grade":34.6154,"ath":1.0,"prod":0.2,"pff":3.0,"lastPPG":16.9683,"bestPPG":20.1583,"wt":231.0,"ht":76.0,"bmi":28.1179,"dash":4.68,"wass":96.3072,"burst":114.6,"careerPA":1321.0,"careerCMP":0.6238,"careerPYd":9710.0,"careerPTD":63.0,"careerINT":33.0,"careerPAPG":28.1064,"careerYPA":7.3505,"careerYPG":206.5957,"careerTDPG":1.3404,"careerINTPG":0.7021,"careerRuYd":960.0,"careerRuYPG":20.4255,"bestPYd":2975.0,"bestPTD":19.0,"bestINT":5.0,"bestCMP":0.647,"bestRuYd":338.0,"careerAcc":0.7218,"careerBTT":0.04,"careerTWP":0.0385,"careerSackPct":0.0635,"bestAcc":0.739,"bestBTT":0.049,"bestTWP":0.025,"bestSackPct":0.043,"rank":null},{"pos":"QB","name":"Jake Fromm","school":"Georgia","conf":"SEC","cfr_id":"jake-fromm-1","pfr_id":"FromJa00","age":21.7699,"round":5.0,"overall":167.0,"years":3,"markers":6,"adjMarkers":2.0,"grade":33.3333,"ath":0.5,"prod":0.3333,"pff":3.0,"lastPPG":14.5857,"bestPPG":15.8043,"wt":219.0,"ht":74.0,"bmi":28.1177,"dash":5.01,"wass":69.5222,"burst":106.5,"careerPA":982.0,"careerCMP":0.6324,"careerPYd":8224.0,"careerPTD":78.0,"careerINT":18.0,"careerPAPG":22.8372,"careerYPA":8.3747,"careerYPG":191.2558,"careerTDPG":1.814,"careerINTPG":0.4186,"careerRuYd":40.0,"careerRuYPG":0.9302,"bestPYd":2860.0,"bestPTD":30.0,"bestINT":5.0,"bestCMP":0.673,"bestRuYd":79.0,"careerAcc":0.7175,"careerBTT":0.0567,"careerTWP":0.0274,"careerSackPct":0.049,"bestAcc":0.757,"bestBTT":0.06,"bestTWP":0.0168,"bestSackPct":0.036,"rank":null},{"pos":"QB","name":"Bryce Perkins","school":"Virginia","conf":"ACC","cfr_id":"bryce-perkins-1","pfr_id":"PerkBr02","age":23.3781,"round":8.0,"years":2,"markers":5,"adjMarkers":1.0,"grade":33.3333,"ath":0.0,"prod":0.3333,"pff":3.0,"lastPPG":25.7443,"bestPPG":26.6462,"careerPA":845.0,"careerCMP":0.645,"careerPYd":6218.0,"careerPTD":47.0,"careerINT":21.0,"careerPAPG":31.2963,"careerYPA":7.3586,"careerYPG":230.2963,"careerTDPG":1.7407,"careerINTPG":0.7778,"careerRuYd":1692.0,"careerRuYPG":62.6667,"bestPYd":3538.0,"bestPTD":25.0,"bestINT":9.0,"bestCMP":0.645,"bestRuYd":923.0,"careerAcc":0.7328,"careerBTT":0.0318,"careerTWP":0.0494,"careerSackPct":0.0807,"bestAcc":0.762,"bestBTT":0.035,"bestTWP":0.0293,"bestSackPct":0.079,"rank":null},{"pos":"QB","name":"Mason Fine","school":"North Texas","conf":"CUSA","cfr_id":"mason-fine-1","age":23.0493,"round":8.0,"years":4,"markers":5,"adjMarkers":1.0,"grade":33.3333,"ath":0.0,"prod":0.3333,"pff":7.0,"lastPPG":19.3933,"bestPPG":20.6708,"careerPA":1655.0,"careerCMP":0.6278,"careerPYd":12505.0,"careerPTD":93.0,"careerINT":34.0,"careerPAPG":33.7755,"careerYPA":7.5559,"careerYPG":255.2041,"careerTDPG":1.898,"careerINTPG":0.6939,"careerRuYd":57.0,"careerRuYPG":1.1633,"bestPYd":4052.0,"bestPTD":31.0,"bestINT":5.0,"bestCMP":0.646,"bestRuYd":118.0,"careerAcc":0.735,"careerBTT":0.0538,"careerTWP":0.0466,"careerSackPct":0.0683,"bestAcc":0.797,"bestBTT":0.063,"bestTWP":0.0294,"bestSackPct":0.045,"rank":null},{"pos":"QB","name":"Kelly Bryant","school":"Missouri","conf":"SEC","cfr_id":"kelly-bryant-1","age":23.6137,"round":8.0,"years":5,"markers":5,"adjMarkers":1.0,"grade":30.7692,"ath":0.5,"prod":0.2667,"pff":3.0,"lastPPG":17.28,"bestPPG":20.6129,"wt":229.0,"ht":75.0,"bmi":28.6228,"dash":4.69,"wass":94.6617,"burst":122.0,"careerPA":762.0,"careerCMP":0.6457,"careerPYd":5553.0,"careerPTD":31.0,"careerINT":16.0,"careerPAPG":19.05,"careerYPA":7.2874,"careerYPG":138.825,"careerTDPG":0.775,"careerINTPG":0.4,"careerRuYd":1215.0,"careerRuYPG":30.375,"bestPYd":2802.0,"bestPTD":15.0,"bestINT":6.0,"bestCMP":0.658,"bestRuYd":665.0,"careerAcc":0.7374,"careerBTT":0.0378,"careerTWP":0.0273,"careerSackPct":0.0565,"bestAcc":0.739,"bestBTT":0.043,"bestTWP":0.0171,"bestSackPct":0.051,"rank":null},{"pos":"QB","name":"Cole McDonald","school":"Hawaii","conf":"MWC","cfr_id":"cole-mcdonald-1","age":21.9644,"round":7.0,"overall":224.0,"years":3,"markers":7,"adjMarkers":1.0,"grade":29.6296,"ath":0.0,"prod":0.4667,"pff":2.0,"lastPPG":25.9786,"bestPPG":26.8385,"wt":215.0,"ht":75.0,"bmi":26.8729,"dash":4.58,"wass":97.7252,"burst":121.7,"careerPA":1004.0,"careerCMP":0.6135,"careerPYd":8032.0,"careerPTD":70.0,"careerINT":24.0,"careerPAPG":30.4242,"careerYPA":8.0,"careerYPG":243.3939,"careerTDPG":2.1212,"careerINTPG":0.7273,"careerRuYd":880.0,"careerRuYPG":26.6667,"bestPYd":4135.0,"bestPTD":36.0,"bestINT":10.0,"bestCMP":0.638,"bestRuYd":383.0,"careerAcc":0.695,"careerBTT":0.0536,"careerTWP":0.0556,"careerSackPct":0.0497,"bestAcc":0.72,"bestBTT":0.055,"bestTWP":0.0465,"bestSackPct":0.036,"rank":null},{"pos":"QB","name":"Riley Neal","school":"Vanderbilt","conf":"SEC","cfr_id":"riley-neal-1","age":23.5945,"round":8.0,"years":5,"markers":4,"adjMarkers":0.0,"grade":29.1667,"ath":0.0,"prod":0.2667,"pff":4.0,"lastPPG":9.1091,"bestPPG":22.3309,"careerPA":1477.0,"careerCMP":0.5958,"careerPYd":8978.0,"careerPTD":55.0,"careerINT":30.0,"careerPAPG":32.8222,"careerYPA":6.0785,"careerYPG":199.5111,"careerTDPG":1.2222,"careerINTPG":0.6667,"careerRuYd":1421.0,"careerRuYPG":31.5778,"bestPYd":2541.0,"bestPTD":16.0,"bestINT":4.0,"bestCMP":0.614,"bestRuYd":540.0,"careerAcc":0.6936,"careerBTT":0.0338,"careerTWP":0.0446,"careerSackPct":0.0398,"bestAcc":0.696,"bestBTT":0.041,"bestTWP":0.021,"bestSackPct":0.028,"rank":null},{"pos":"QB","name":"J'mar Smith","school":"Louisiana Tech","conf":"CUSA","cfr_id":"jmar-smith-1","age":23.6164,"round":8.0,"years":4,"markers":4,"adjMarkers":0.0,"grade":29.1667,"ath":0.0,"prod":0.2667,"pff":5.0,"lastPPG":21.4982,"bestPPG":21.4982,"careerPA":1280.0,"careerCMP":0.593,"careerPYd":9523.0,"careerPTD":51.0,"careerINT":21.0,"careerPAPG":28.4444,"careerYPA":7.4398,"careerYPG":211.6222,"careerTDPG":1.1333,"careerINTPG":0.4667,"careerRuYd":877.0,"careerRuYPG":19.4889,"bestPYd":3160.0,"bestPTD":18.0,"bestINT":5.0,"bestCMP":0.643,"bestRuYd":378.0,"careerAcc":0.7077,"careerBTT":0.0527,"careerTWP":0.0372,"careerSackPct":0.06,"bestAcc":0.72,"bestBTT":0.069,"bestTWP":0.019,"bestSackPct":0.053,"rank":null},{"pos":"QB","name":"Brandon Wimbush","school":"UCF","conf":"American","cfr_id":"brandon-wimbush-1","age":23.3863,"round":8.0,"years":4,"markers":4,"adjMarkers":0.0,"grade":29.1667,"ath":0.0,"prod":0.2667,"pff":0.0,"lastPPG":3.896,"bestPPG":24.7583,"careerPA":406.0,"careerCMP":0.5074,"careerPYd":2773.0,"careerPTD":22.0,"careerINT":12.0,"careerPAPG":16.24,"careerYPA":6.83,"careerYPG":110.92,"careerTDPG":0.88,"careerINTPG":0.48,"careerRuYd":1203.0,"careerRuYPG":48.12,"bestPYd":1870.0,"bestPTD":16.0,"bestINT":6.0,"bestCMP":0.529,"bestRuYd":803.0,"careerAcc":0.6201,"careerBTT":0.0542,"careerTWP":0.0665,"careerSackPct":0.0686,"bestAcc":0.624,"bestBTT":0.059,"bestTWP":0.0455,"bestSackPct":0.07,"rank":null},{"pos":"QB","name":"Shea Patterson","school":"Michigan","conf":"Big Ten","cfr_id":"shea-patterson-1","age":23.3014,"round":8.0,"years":4,"markers":4,"adjMarkers":0.0,"grade":26.9231,"ath":0.0,"prod":0.3333,"pff":5.0,"lastPPG":18.5723,"bestPPG":24.3667,"wt":212.0,"ht":73.0,"bmi":27.9698,"dash":4.71,"wass":86.1553,"burst":110.7,"careerPA":1098.0,"careerCMP":0.6029,"careerPYd":8800.0,"careerPTD":68.0,"careerINT":27.0,"careerPAPG":30.5,"careerYPA":8.0146,"careerYPG":244.4444,"careerTDPG":1.8889,"careerINTPG":0.75,"careerRuYd":476.0,"careerRuYPG":13.2222,"bestPYd":3061.0,"bestPTD":23.0,"bestINT":3.0,"bestCMP":0.646,"bestRuYd":273.0,"careerAcc":0.7025,"careerBTT":0.0571,"careerTWP":0.0417,"careerSackPct":0.0587,"bestAcc":0.739,"bestBTT":0.07,"bestTWP":0.0299,"bestSackPct":0.051,"rank":null},{"pos":"QB","name":"Brian Lewerke","school":"Michigan State","conf":"Big Ten","cfr_id":"brian-lewerke-1","age":23.5342,"round":8.0,"years":4,"markers":4,"adjMarkers":0.0,"grade":26.9231,"ath":0.0,"prod":0.2667,"pff":4.0,"lastPPG":18.0892,"bestPPG":20.9323,"wt":213.0,"ht":74.0,"bmi":27.3473,"dash":4.95,"wass":70.9559,"burst":109.2,"careerPA":1249.0,"careerCMP":0.5773,"careerPYd":8293.0,"careerPTD":47.0,"careerINT":32.0,"careerPAPG":30.4634,"careerYPA":6.6397,"careerYPG":202.2683,"careerTDPG":1.1463,"careerINTPG":0.7805,"careerRuYd":1255.0,"careerRuYPG":30.6098,"bestPYd":3079.0,"bestPTD":20.0,"bestINT":7.0,"bestCMP":0.596,"bestRuYd":559.0,"careerAcc":0.6764,"careerBTT":0.035,"careerTWP":0.0477,"careerSackPct":0.0449,"bestAcc":0.706,"bestBTT":0.041,"bestTWP":0.0333,"bestSackPct":0.04,"rank":null},{"pos":"QB","name":"Khalil Tate","school":"Arizona","conf":"Pac-12","cfr_id":"khalil-tate-1","age":21.537,"round":8.0,"years":4,"markers":3,"adjMarkers":-1.0,"grade":25.0,"ath":0.0,"prod":0.2,"pff":5.0,"lastPPG":16.5873,"bestPPG":29.4309,"careerPA":792.0,"careerCMP":0.5795,"careerPYd":6318.0,"careerPTD":57.0,"careerINT":31.0,"careerPAPG":19.8,"careerYPA":7.9773,"careerYPG":157.95,"careerTDPG":1.425,"careerINTPG":0.775,"careerRuYd":2285.0,"careerRuYPG":57.125,"bestPYd":2530.0,"bestPTD":26.0,"bestINT":8.0,"bestCMP":0.62,"bestRuYd":1411.0,"careerAcc":0.6767,"careerBTT":0.0714,"careerTWP":0.0539,"careerSackPct":0.0505,"bestAcc":0.707,"bestBTT":0.073,"bestTWP":0.0341,"bestSackPct":0.035,"rank":null},{"pos":"QB","name":"James Morgan","school":"Florida International","conf":"CUSA","cfr_id":"james-morgan-1","age":23.1863,"round":4.0,"overall":125.0,"years":4,"markers":2,"adjMarkers":-1.0,"grade":22.2222,"ath":0.5,"prod":0.0667,"pff":3.0,"lastPPG":12.4154,"bestPPG":17.515,"wt":229.0,"ht":76.0,"bmi":27.8745,"dash":4.89,"wass":80.0995,"burst":105.3,"careerPA":1221.0,"careerCMP":0.5725,"careerPYd":8629.0,"careerPTD":65.0,"careerINT":34.0,"careerPAPG":27.75,"careerYPA":7.0672,"careerYPG":196.1136,"careerTDPG":1.4773,"careerINTPG":0.7727,"careerRuYd":-168.0,"careerRuYPG":-3.8182,"bestPYd":2727.0,"bestPTD":26.0,"bestINT":5.0,"bestCMP":0.653,"bestRuYd":-19.0,"careerAcc":0.6687,"careerBTT":0.0466,"careerTWP":0.0564,"careerSackPct":0.0391,"bestAcc":0.71,"bestBTT":0.071,"bestTWP":0.0472,"bestSackPct":0.027,"rank":null},{"pos":"QB","name":"Alex Hornibrook","school":"Florida State","conf":"ACC","cfr_id":"alex-hornibrook-1","age":23.2959,"round":8.0,"years":4,"markers":2,"adjMarkers":-2.0,"grade":20.8333,"ath":0.0,"prod":0.1333,"pff":2.0,"lastPPG":11.988,"bestPPG":13.04,"careerPA":826.0,"careerCMP":0.6174,"careerPYd":6424.0,"careerPTD":54.0,"careerINT":35.0,"careerPAPG":20.1463,"careerYPA":7.7772,"careerYPG":156.6829,"careerTDPG":1.3171,"careerINTPG":0.8537,"careerRuYd":-314.0,"careerRuYPG":-7.6585,"bestPYd":2644.0,"bestPTD":25.0,"bestINT":2.0,"bestCMP":0.689,"bestRuYd":-61.0,"careerAcc":0.7248,"careerBTT":0.0505,"careerTWP":0.0613,"careerSackPct":0.0726,"bestAcc":0.798,"bestBTT":0.07,"bestTWP":0.04,"bestSackPct":0.053,"rank":null},{"pos":"QB","name":"Josh Love","school":"San Jose State","conf":"MWC","cfr_id":"josh-love-1","age":23.6493,"round":8.0,"years":4,"markers":2,"adjMarkers":-2.0,"grade":20.8333,"ath":0.0,"prod":0.1333,"pff":4.0,"lastPPG":20.51,"bestPPG":20.51,"careerPA":1000.0,"careerCMP":0.578,"careerPYd":7206.0,"careerPTD":43.0,"careerINT":29.0,"careerPAPG":24.3902,"careerYPA":7.206,"careerYPG":175.7561,"careerTDPG":1.0488,"careerINTPG":0.7073,"careerRuYd":-282.0,"careerRuYPG":-6.878,"bestPYd":3923.0,"bestPTD":22.0,"bestINT":7.0,"bestCMP":0.609,"bestRuYd":-41.0,"careerAcc":0.6886,"careerBTT":0.054,"careerTWP":0.043,"careerSackPct":0.0482,"bestAcc":0.716,"bestBTT":0.06,"bestTWP":0.0252,"bestSackPct":0.026,"rank":null},{"pos":"QB","name":"Tommy Stevens","school":"Mississippi State","conf":"SEC","cfr_id":"tommy-stevens-1","pfr_id":"StevTo01","age":23.3918,"round":7.0,"overall":240.0,"years":4,"markers":4,"adjMarkers":-2.0,"grade":20.0,"ath":0.0,"prod":0.2667,"pff":0.0,"lastPPG":16.3667,"bestPPG":16.3667,"careerPA":202.0,"careerCMP":0.599,"careerPYd":1459.0,"careerPTD":15.0,"careerINT":6.0,"careerPAPG":6.3125,"careerYPA":7.2228,"careerYPG":45.5938,"careerTDPG":0.4688,"careerINTPG":0.1875,"careerRuYd":887.0,"careerRuYPG":27.7188,"bestPYd":1155.0,"bestPTD":11.0,"bestINT":5.0,"bestCMP":0.602,"bestRuYd":381.0,"careerAcc":0.7259,"careerBTT":0.0545,"careerTWP":0.0644,"careerSackPct":0.083,"bestAcc":0.72,"bestBTT":0.048,"bestTWP":0.0556,"bestSackPct":0.081,"rank":null},{"pos":"QB","name":"Jacob Eason","school":"Washington","conf":"Pac-12","cfr_id":"jacob-eason-1","pfr_id":"EasoJa00","age":22.4712,"round":4.0,"overall":122.0,"years":3,"markers":1,"adjMarkers":-2.0,"grade":18.5185,"ath":0.5,"prod":0.0,"pff":4.0,"lastPPG":16.0677,"bestPPG":16.0677,"wt":231.0,"ht":78.0,"bmi":26.6945,"dash":4.89,"wass":80.7991,"burst":101.75,"careerPA":782.0,"careerCMP":0.5985,"careerPYd":5590.0,"careerPTD":39.0,"careerINT":16.0,"careerPAPG":25.2258,"careerYPA":7.1483,"careerYPG":180.3226,"careerTDPG":1.2581,"careerINTPG":0.5161,"careerRuYd":-126.0,"careerRuYPG":-4.0645,"bestPYd":3132.0,"bestPTD":23.0,"bestINT":8.0,"bestCMP":0.642,"bestRuYd":-12.0,"careerAcc":0.7158,"careerBTT":0.0546,"careerTWP":0.0318,"careerSackPct":0.0517,"bestAcc":0.749,"bestBTT":0.054,"bestTWP":0.0275,"bestSackPct":0.049,"rank":null},{"pos":"QB","name":"Jake Luton","school":"Oregon State","conf":"Pac-12","cfr_id":"jake-luton-1","pfr_id":"LutoJa00","age":24.0712,"round":6.0,"overall":189.0,"years":4,"markers":3,"adjMarkers":-2.0,"grade":18.5185,"ath":0.5,"prod":0.1333,"pff":3.0,"lastPPG":19.5327,"bestPPG":19.5327,"wt":224.0,"ht":78.0,"bmi":25.8856,"careerPA":795.0,"careerCMP":0.6214,"careerPYd":5610.0,"careerPTD":43.0,"careerINT":15.0,"careerPAPG":25.6452,"careerYPA":7.0566,"careerYPG":180.9677,"careerTDPG":1.3871,"careerINTPG":0.4839,"careerRuYd":-131.0,"careerRuYPG":-4.2258,"bestPYd":2714.0,"bestPTD":28.0,"bestINT":3.0,"bestCMP":0.625,"bestRuYd":73.0,"careerAcc":0.7192,"careerBTT":0.0389,"careerTWP":0.0276,"careerSackPct":0.0586,"bestAcc":0.741,"bestBTT":0.051,"bestTWP":0.0164,"bestSackPct":0.047,"rank":null},{"pos":"QB","name":"Nathan Stanley","school":"Iowa","conf":"Big Ten","cfr_id":"nathan-stanley-2","age":22.6959,"round":7.0,"overall":244.0,"years":4,"markers":3,"adjMarkers":-3.0,"grade":14.8148,"ath":1.0,"prod":0.0667,"pff":5.0,"lastPPG":13.98,"bestPPG":16.3985,"wt":235.0,"ht":76.0,"bmi":28.6048,"dash":4.81,"wass":87.8047,"burst":102.45,"careerPA":1155.0,"careerCMP":0.5827,"careerPYd":8302.0,"careerPTD":68.0,"careerINT":23.0,"careerPAPG":25.6667,"careerYPA":7.1879,"careerYPG":184.4889,"careerTDPG":1.5111,"careerINTPG":0.5111,"careerRuYd":-104.0,"careerRuYPG":-2.3111,"bestPYd":2951.0,"bestPTD":26.0,"bestINT":6.0,"bestCMP":0.594,"bestRuYd":7.0,"careerAcc":0.6995,"careerBTT":0.0587,"careerTWP":0.0328,"careerSackPct":0.0506,"bestAcc":0.73,"bestBTT":0.066,"bestTWP":0.0205,"bestSackPct":0.035,"rank":null},{"pos":"QB","name":"Ben DiNucci","school":"Pittsburgh","conf":"ACC","cfr_id":"ben-dinucci-1","pfr_id":"DiNuBe00","age":23.4493,"round":7.0,"overall":231.0,"years":2,"markers":1,"adjMarkers":-5.0,"grade":8.0,"ath":0.0,"prod":0.1333,"pff":0.0,"lastPPG":7.724,"bestPPG":7.724,"careerPA":167.0,"careerCMP":0.5449,"careerPYd":1107.0,"careerPTD":6.0,"careerINT":7.0,"careerPAPG":13.9167,"careerYPA":6.6287,"careerYPG":92.25,"careerTDPG":0.5,"careerINTPG":0.5833,"careerRuYd":144.0,"careerRuYPG":12.0,"bestPYd":1091.0,"bestPTD":5.0,"bestINT":5.0,"bestCMP":0.557,"bestRuYd":126.0,"careerAcc":0.6689,"careerBTT":0.0476,"careerTWP":0.0893,"careerSackPct":0.0693,"bestAcc":0.678,"bestBTT":0.043,"bestTWP":0.0677,"bestSackPct":0.073,"rank":null},{"pos":"RB","name":"Jonathan Taylor","school":"Wisconsin","conf":"Big Ten","cfr_id":"jonathan-taylor-1","pfr_id":"TaylJo02","age":21.2959,"round":2.0,"overall":41.0,"years":3,"markers":12,"adjMarkers":13.0,"grade":90.9091,"ath":1.0,"prod":1.0,"pff":9.0,"lastPPG":29.1071,"bestPPG":29.1071,"wt":226.0,"ht":70.0,"bmi":32.4273,"dash":4.39,"wass":121.6971,"burst":122.7,"ypc":6.6674,"yptp":2.3853,"bestRec":26.0,"bestTotalYds":2254.0,"firstPPG":20.9429,"careerBA":0.1005,"careerMTF":0.2378,"career1D":0.3157,"careerYACO":4.2378,"careerYPRR":1.6583,"careerTPRR":0.2708,"bestBA":0.1111,"bestMTF":0.2719,"best1D":0.3375,"bestYACO":4.53,"bestYPRR":2.13,"bestTPRR":0.3246,"rank":null},{"pos":"RB","name":"Cam Akers","school":"Florida State","conf":"ACC","cfr_id":"cam-akers-1","pfr_id":"AkerCa00","age":20.874,"round":2.0,"overall":52.0,"years":3,"markers":12,"adjMarkers":13.0,"grade":90.9091,"ath":1.0,"prod":0.8,"pff":2.0,"lastPPG":25.1727,"bestPPG":25.1727,"wt":217.0,"ht":70.0,"bmi":31.136,"dash":4.47,"wass":108.7075,"burst":121.35,"ypc":4.9044,"yptp":1.2928,"bestRec":30.0,"bestTotalYds":1140.0,"firstPPG":13.8369,"careerBA":0.0648,"careerMTF":0.2457,"career1D":0.2628,"careerYACO":3.7304,"careerYPRR":0.9271,"careerTPRR":0.1651,"bestBA":0.0674,"bestMTF":0.329,"best1D":0.2944,"bestYACO":3.91,"bestYPRR":1.15,"bestTPRR":0.1939,"rank":null},{"pos":"RB","name":"J.K. Dobbins","school":"Ohio State","conf":"Big Ten","cfr_id":"jk-dobbins-1","pfr_id":"DobbJK00","age":21.3863,"round":2.0,"overall":55.0,"years":3,"markers":9,"adjMarkers":10.0,"grade":89.4737,"ath":0.5,"prod":1.0,"pff":4.0,"lastPPG":27.5714,"bestPPG":27.5714,"wt":209.0,"ht":69.0,"bmi":30.8636,"ypc":6.1503,"yptp":1.602,"bestRec":26.0,"bestTotalYds":1538.0,"firstPPG":15.9857,"careerBA":0.0799,"careerMTF":0.1956,"career1D":0.3196,"careerYACO":3.6529,"careerYPRR":1.0031,"careerTPRR":0.1306,"bestBA":0.1031,"bestMTF":0.2425,"best1D":0.3289,"bestYACO":4.25,"bestYPRR":1.17,"bestTPRR":0.1327,"rank":null},{"pos":"RB","name":"D'Andre Swift","school":"Georgia","conf":"SEC","cfr_id":"dandre-swift-1","pfr_id":"SwifDA00","age":21.3096,"round":2.0,"overall":35.0,"years":3,"markers":10,"adjMarkers":11.0,"grade":81.8182,"ath":1.0,"prod":0.6,"pff":10.0,"lastPPG":15.3857,"bestPPG":17.4714,"wt":212.0,"ht":68.0,"bmi":32.2342,"dash":4.48,"wass":105.2577,"burst":120.85,"ypc":6.5568,"yptp":1.275,"bestRec":32.0,"bestTotalYds":1346.0,"firstPPG":7.8733,"careerBA":0.1043,"careerMTF":0.2109,"career1D":0.3129,"careerYACO":3.8277,"careerYPRR":1.5346,"careerTPRR":0.2074,"bestBA":0.1235,"bestMTF":0.227,"best1D":0.3457,"bestYACO":4.37,"bestYPRR":2.1,"bestTPRR":0.3014,"rank":null},{"pos":"RB","name":"AJ Dillon","school":"Boston College","conf":"ACC","cfr_id":"aj-dillon-1","pfr_id":"DillAJ00","age":22.0137,"round":2.0,"overall":62.0,"years":3,"markers":10,"adjMarkers":11.0,"grade":81.8182,"ath":1.0,"prod":0.4,"pff":2.0,"lastPPG":22.3846,"bestPPG":22.3846,"wt":247.0,"ht":73.0,"bmi":32.5874,"dash":4.53,"wass":117.3098,"burst":135.2,"ypc":5.1858,"yptp":1.6422,"bestRec":13.0,"bestTotalYds":1589.0,"firstPPG":18.6846,"careerBA":0.0653,"careerMTF":0.2352,"career1D":0.2542,"careerYACO":3.5392,"careerYPRR":0.8741,"careerTPRR":0.1,"bestBA":0.0664,"bestMTF":0.2555,"best1D":0.2997,"bestYACO":3.88,"bestYPRR":1.56,"bestTPRR":0.128,"rank":null},{"pos":"RB","name":"Clyde Edwards-Helaire","school":"LSU","conf":"SEC","cfr_id":"clyde-edwards-helaire-1","pfr_id":"EdwaCl00","age":21.0712,"round":1.0,"overall":32.0,"years":3,"markers":7,"adjMarkers":10.0,"grade":77.2727,"ath":0.6667,"prod":0.4,"pff":7.0,"lastPPG":22.9133,"bestPPG":22.9133,"wt":207.0,"ht":67.0,"bmi":32.4205,"dash":4.6,"wass":92.4632,"burst":128.65,"ypc":5.6838,"yptp":0.946,"bestRec":55.0,"bestTotalYds":754.0,"firstPPG":0.8231,"careerBA":0.0865,"careerMTF":0.2892,"career1D":0.3297,"careerYACO":3.4486,"careerYPRR":1.2202,"careerTPRR":0.1626,"bestBA":0.0981,"bestMTF":0.3333,"best1D":0.3645,"bestYACO":3.65,"bestYPRR":11.5,"bestTPRR":0.75,"rank":null},{"pos":"RB","name":"Zack Moss","school":"Utah","conf":"Pac-12","cfr_id":"zack-moss-1","pfr_id":"MossZa00","age":22.3918,"round":3.0,"overall":86.0,"years":4,"markers":7,"adjMarkers":7.0,"grade":66.6667,"ath":0.5,"prod":0.6,"pff":8.0,"lastPPG":23.8769,"bestPPG":23.8769,"wt":223.0,"ht":69.0,"bmi":32.931,"dash":4.65,"wass":95.3944,"ypc":5.7121,"yptp":1.2642,"bestRec":29.0,"bestTotalYds":1416.0,"firstPPG":5.16,"careerBA":0.0859,"careerMTF":0.3014,"career1D":0.3211,"careerYACO":3.7761,"careerYPRR":1.084,"careerTPRR":0.122,"bestBA":0.0986,"bestMTF":0.3803,"best1D":0.338,"bestYACO":4.45,"bestYPRR":2.36,"bestTPRR":0.189,"rank":null},{"pos":"RB","name":"Antonio Gibson","school":"Memphis","conf":"American","cfr_id":"antonio-gibson-2","pfr_id":"GibsAn00","age":21.8712,"round":3.0,"overall":66.0,"years":2,"markers":7,"adjMarkers":7.0,"grade":63.6364,"ath":0.8333,"prod":0.6,"pff":11.0,"lastPPG":15.7429,"bestPPG":15.7429,"wt":228.0,"ht":73.0,"bmi":30.0807,"dash":4.39,"wass":122.7741,"burst":118.5,"ypc":11.1818,"yptp":0.6042,"bestRec":38.0,"bestTotalYds":1104.0,"firstPPG":1.9929,"careerBA":0.1818,"careerMTF":0.4848,"career1D":0.4848,"careerYACO":7.7273,"careerYPRR":2.2273,"careerTPRR":0.1758,"bestBA":0.1818,"bestMTF":0.4848,"best1D":0.4848,"bestYACO":7.73,"bestYPRR":2.23,"bestTPRR":0.1758,"rank":null},{"pos":"RB","name":"Darrynton Evans","school":"Appalachian State","conf":"Sun Belt","cfr_id":"darrynton-evans-1","pfr_id":"EvanDa02","age":21.8274,"round":3.0,"overall":93.0,"years":3,"markers":7,"adjMarkers":7.0,"grade":63.6364,"ath":0.8333,"prod":0.4,"pff":3.0,"lastPPG":23.3829,"bestPPG":23.3829,"wt":203.0,"ht":70.0,"bmi":29.1272,"dash":4.41,"wass":107.3425,"burst":125.4,"ypc":5.9834,"yptp":1.1793,"bestRec":21.0,"bestTotalYds":1274.0,"firstPPG":2.5917,"careerBA":0.0934,"careerMTF":0.1846,"career1D":0.2573,"careerYACO":3.2739,"careerYPRR":0.9726,"careerTPRR":0.1677,"bestBA":0.118,"bestMTF":0.1953,"best1D":0.2695,"bestYACO":3.9,"bestYPRR":1.23,"bestTPRR":0.3462,"rank":null},{"pos":"RB","name":"Ke'Shawn Vaughn","school":"Vanderbilt","conf":"SEC","cfr_id":"keshawn-vaughn-1","pfr_id":"VaugKe00","age":23.0082,"round":3.0,"overall":76.0,"years":4,"markers":5,"adjMarkers":5.0,"grade":54.5455,"ath":0.6667,"prod":0.2,"pff":10.0,"lastPPG":18.3667,"bestPPG":19.8667,"wt":214.0,"ht":70.0,"bmi":30.7055,"dash":4.51,"wass":103.4517,"burst":112.9,"ypc":5.7622,"yptp":1.2445,"bestRec":29.0,"bestTotalYds":842.0,"firstPPG":12.3818,"careerBA":0.0768,"careerMTF":0.2391,"career1D":0.2565,"careerYACO":3.8534,"careerYPRR":1.2824,"careerTPRR":0.1702,"bestBA":0.121,"bestMTF":0.2803,"best1D":0.3185,"bestYACO":5.28,"bestYPRR":1.89,"bestTPRR":0.2553,"rank":null},{"pos":"RB","name":"Joshua Kelley","school":"UCLA","conf":"Pac-12","cfr_id":"joshua-kelley-1","pfr_id":"KellJo01","age":22.4603,"round":4.0,"overall":112.0,"years":2,"markers":7,"adjMarkers":4.0,"grade":50.0,"ath":0.6667,"prod":0.4,"pff":1.0,"lastPPG":18.3727,"bestPPG":22.0545,"wt":212.0,"ht":71.0,"bmi":29.5677,"dash":4.49,"wass":104.3231,"burst":113.2,"ypc":5.0727,"yptp":1.4602,"bestRec":27.0,"bestTotalYds":1436.0,"firstPPG":22.0545,"careerBA":0.0595,"careerMTF":0.1718,"career1D":0.2643,"careerYACO":2.826,"careerYPRR":0.7078,"careerTPRR":0.1314,"bestBA":0.08,"bestMTF":0.1921,"best1D":0.2667,"bestYACO":2.85,"bestYPRR":0.85,"bestTPRR":0.1498,"rank":null},{"pos":"RB","name":"Anthony McFarland","school":"Maryland","conf":"Big Ten","cfr_id":"anthony-mcfarland-2","age":22.1753,"round":4.0,"overall":124.0,"years":2,"markers":6,"adjMarkers":3.0,"grade":45.4545,"ath":0.8333,"prod":0.4,"pff":4.0,"lastPPG":13.1818,"bestPPG":13.1818,"wt":208.0,"ht":68.0,"bmi":31.626,"dash":4.44,"wass":107.0438,"burst":108.15,"ypc":6.7265,"yptp":1.2471,"bestRec":17.0,"bestTotalYds":1107.0,"firstPPG":11.8083,"careerBA":0.1224,"careerMTF":0.2286,"career1D":0.2694,"careerYACO":3.3796,"careerYPRR":0.869,"careerTPRR":0.1397,"bestBA":0.1679,"bestMTF":0.2456,"best1D":0.3053,"bestYACO":3.91,"bestYPRR":0.88,"bestTPRR":0.1575,"rank":null},{"pos":"RB","name":"Eno Benjamin","school":"Arizona State","conf":"Pac-12","cfr_id":"eno-benjamin-1","pfr_id":"BenjEn00","age":21.0658,"round":7.0,"overall":329.0,"years":3,"markers":9,"adjMarkers":3.0,"grade":45.4545,"ath":0.6667,"prod":0.8,"pff":5.0,"lastPPG":21.4167,"bestPPG":25.6538,"wt":207.0,"ht":69.0,"bmi":30.5683,"dash":4.57,"wass":94.9152,"burst":127.3,"ypc":4.9774,"yptp":1.3079,"bestRec":42.0,"bestTotalYds":1905.0,"firstPPG":2.67,"careerBA":0.0781,"careerMTF":0.2691,"career1D":0.2865,"careerYACO":3.2205,"careerYPRR":0.9272,"careerTPRR":0.1501,"bestBA":0.1739,"bestMTF":0.3913,"best1D":0.3478,"bestYACO":3.91,"bestYPRR":1.07,"bestTPRR":0.161,"rank":null},{"pos":"RB","name":"Lamical Perine","school":"Florida","conf":"SEC","cfr_id":"lamical-perine-1","age":22.2658,"round":4.0,"overall":120.0,"years":4,"markers":4,"adjMarkers":1.0,"grade":36.3636,"ath":0.5,"prod":0.2,"pff":5.0,"lastPPG":15.3692,"bestPPG":15.3692,"wt":216.0,"ht":71.0,"bmi":30.1256,"dash":4.62,"wass":94.8235,"burst":118.5,"ypc":5.0406,"yptp":0.9584,"bestRec":40.0,"bestTotalYds":643.0,"firstPPG":6.0923,"careerBA":0.0649,"careerMTF":0.1704,"career1D":0.2556,"careerYACO":3.14,"careerYPRR":1.1596,"careerTPRR":0.1562,"bestBA":0.0896,"bestMTF":0.2059,"best1D":0.3209,"bestYACO":3.73,"bestYPRR":3.08,"bestTPRR":0.2075,"rank":null},{"pos":"RB","name":"Deejay Dallas","school":"Miami (FL)","conf":"ACC","cfr_id":"deejay-dallas-1","pfr_id":"DallDe00","age":21.6384,"round":4.0,"overall":144.0,"years":3,"markers":3,"adjMarkers":0.0,"grade":31.8182,"ath":0.5,"prod":0.0,"pff":7.0,"lastPPG":15.73,"bestPPG":15.73,"wt":217.0,"ht":70.0,"bmi":31.136,"dash":4.58,"wass":98.6343,"burst":116.45,"ypc":5.7623,"yptp":0.7254,"bestRec":14.0,"bestTotalYds":702.0,"firstPPG":4.4083,"careerBA":0.1094,"careerMTF":0.3057,"career1D":0.2717,"careerYACO":3.7019,"careerYPRR":1.0709,"careerTPRR":0.1047,"bestBA":0.1193,"bestMTF":0.3415,"best1D":0.2783,"bestYACO":4.24,"bestYPRR":2.09,"bestTPRR":0.1196,"rank":null},{"pos":"RB","name":"Michael Warren II","school":"Cincinnati","conf":"American","cfr_id":"michael-warren-ii-1","age":21.4822,"round":8.0,"years":3,"markers":6,"adjMarkers":-1.0,"grade":31.5789,"ath":0.5,"prod":0.6,"pff":6.0,"lastPPG":18.4857,"bestPPG":25.0917,"wt":226.0,"ht":69.0,"bmi":33.3741,"ypc":5.22,"yptp":1.2285,"bestRec":25.0,"bestTotalYds":1561.0,"firstPPG":4.0917,"careerBA":0.0645,"careerMTF":0.2599,"career1D":0.2939,"careerYACO":3.7545,"careerYPRR":0.8245,"careerTPRR":0.1189,"bestBA":0.1296,"bestMTF":0.2923,"best1D":0.332,"bestYACO":3.88,"bestYPRR":0.9,"bestTPRR":0.127,"rank":null},{"pos":"RB","name":"Jason Huntley","school":"New Mexico State","conf":"Ind","cfr_id":"jason-huntley-1","pfr_id":"HuntJa01","age":22.0466,"round":5.0,"overall":172.0,"years":4,"markers":2,"adjMarkers":-2.0,"grade":29.4118,"ath":0.1667,"prod":0.2,"pff":10.0,"lastPPG":19.5167,"bestPPG":19.5167,"ypc":5.8499,"yptp":0.9126,"bestRec":47.0,"bestTotalYds":783.0,"firstPPG":3.1091,"careerBA":0.0871,"careerMTF":0.2823,"career1D":0.314,"careerYACO":3.3588,"careerYPRR":1.3602,"careerTPRR":0.2174,"bestBA":0.1447,"bestMTF":0.3333,"best1D":0.3585,"bestYACO":4.39,"bestYPRR":1.67,"bestTPRR":0.2283,"rank":null},{"pos":"RB","name":"Malcolm Perry","school":"Navy","conf":"American","cfr_id":"malcolm-perry-1","age":23.0493,"round":7.0,"overall":246.0,"years":4,"markers":5,"adjMarkers":-1.0,"grade":27.2727,"ath":0.1667,"prod":0.8,"pff":11.0,"lastPPG":30.4662,"bestPPG":30.4662,"wt":186.0,"ht":69.0,"bmi":27.4671,"dash":4.63,"wass":80.9504,"burst":122.2,"ypc":7.0993,"yptp":1.3534,"bestRec":13.0,"bestTotalYds":1485.0,"firstPPG":4.4333,"careerBA":0.1133,"careerMTF":0.2767,"career1D":0.3283,"careerYACO":3.93,"careerYPRR":3.4074,"careerTPRR":0.3111,"bestBA":0.2222,"bestMTF":0.4444,"best1D":0.4444,"bestYACO":4.19,"bestYPRR":4.19,"rank":null},{"pos":"RB","name":"James Robinson","school":"Illinois State","conf":"FCS","pfr_id":"RobiJa00","age":21.7425,"round":8.0,"years":4,"markers":6,"adjMarkers":-1.0,"grade":27.2727,"ath":0.6667,"prod":0.4,"lastPPG":21.58,"bestPPG":22.2182,"wt":219.0,"ht":69.0,"bmi":32.34,"dash":4.64,"wass":94.4936,"burst":130.5,"ypc":5.74,"bestRec":21.0,"bestTotalYds":1008.0,"firstPPG":8.1222,"rank":null},{"pos":"RB","name":"Jonathan Ward","school":"Central Michigan","conf":"MAC","cfr_id":"jonathan-ward-3","pfr_id":"WardJo00","age":22.6,"round":8.0,"years":4,"markers":4,"adjMarkers":-3.0,"grade":23.5294,"ath":0.1667,"prod":0.6,"pff":6.0,"lastPPG":22.8083,"bestPPG":22.8083,"ypc":5.3523,"yptp":0.9607,"bestRec":48.0,"bestTotalYds":1487.0,"firstPPG":6.0175,"careerBA":0.0682,"careerMTF":0.2132,"career1D":0.2559,"careerYACO":3.3731,"careerYPRR":1.4266,"careerTPRR":0.232,"bestBA":0.0852,"bestMTF":0.2466,"best1D":0.3207,"bestYACO":3.95,"bestYPRR":1.97,"bestTPRR":0.3143,"rank":null},{"pos":"RB","name":"JaMycal Hasty","school":"Baylor","conf":"Big 12","cfr_id":"jamycal-hasty-1","pfr_id":"HastJa02","age":23.6493,"round":8.0,"years":4,"markers":5,"adjMarkers":-2.0,"grade":22.7273,"ath":0.6667,"prod":0.2,"pff":5.0,"lastPPG":10.5786,"bestPPG":10.5818,"wt":205.0,"ht":68.0,"bmi":31.1699,"dash":4.55,"wass":95.6617,"burst":127.8,"ypc":5.1762,"yptp":0.636,"bestRec":26.0,"bestTotalYds":649.0,"firstPPG":7.1583,"careerBA":0.0829,"careerMTF":0.215,"career1D":0.285,"careerYACO":2.9352,"careerYPRR":0.9327,"careerTPRR":0.1865,"bestBA":0.1101,"bestMTF":0.3537,"best1D":0.3277,"bestYACO":3.84,"bestYPRR":1.49,"bestTPRR":0.2895,"rank":null},{"pos":"RB","name":"Rico Dowdle","school":"South Carolina","conf":"SEC","cfr_id":"rico-dowdle-1","pfr_id":"DowdRi01","age":21.9233,"round":8.0,"years":4,"markers":5,"adjMarkers":-2.0,"grade":22.7273,"ath":0.8333,"prod":0.0,"pff":2.0,"lastPPG":11.25,"bestPPG":15.4333,"wt":213.0,"ht":71.0,"bmi":29.7072,"dash":4.54,"wass":100.2735,"burst":128.1,"ypc":5.0631,"yptp":0.7806,"bestRec":22.0,"bestTotalYds":819.0,"firstPPG":15.4333,"careerBA":0.0771,"careerMTF":0.1846,"career1D":0.257,"careerYACO":3.1822,"careerYPRR":0.8895,"careerTPRR":0.1529,"bestBA":0.0976,"bestMTF":0.2164,"best1D":0.2687,"bestYACO":3.36,"bestYPRR":1.56,"bestTPRR":0.1707,"rank":null},{"pos":"RB","name":"Raymond Calais","school":"Louisiana","conf":"Sun Belt","cfr_id":"raymond-calais-1","age":22.0959,"round":7.0,"overall":245.0,"years":4,"markers":3,"adjMarkers":-3.0,"grade":18.1818,"ath":0.5,"prod":0.2,"pff":6.0,"lastPPG":10.5214,"bestPPG":10.5214,"wt":188.0,"ht":68.0,"bmi":28.585,"dash":4.42,"wass":98.5142,"burst":123.75,"ypc":7.8178,"yptp":0.5519,"bestRec":10.0,"bestTotalYds":117.0,"firstPPG":1.9667,"careerBA":0.1207,"careerMTF":0.1724,"career1D":0.3405,"careerYACO":3.8966,"careerYPRR":0.815,"careerTPRR":0.105,"bestBA":0.1375,"bestMTF":0.1947,"best1D":0.3717,"bestYACO":5.03,"bestYPRR":1.29,"bestTPRR":0.125,"rank":null},{"pos":"RB","name":"Ben LeMay","school":"Charlotte","conf":"CUSA","cfr_id":"ben-lemay-1","age":22.5507,"round":8.0,"years":4,"markers":4,"adjMarkers":-3.0,"grade":18.1818,"ath":0.5,"prod":0.2,"pff":5.0,"lastPPG":20.8545,"bestPPG":20.8545,"wt":221.0,"ht":68.0,"bmi":33.6026,"dash":4.75,"wass":86.8256,"burst":104.45,"ypc":5.4228,"yptp":1.178,"bestRec":21.0,"bestTotalYds":820.0,"firstPPG":2.53,"careerBA":0.072,"careerMTF":0.2496,"career1D":0.2546,"careerYACO":3.5025,"careerYPRR":1.1985,"careerTPRR":0.1248,"bestBA":0.0882,"bestMTF":0.3529,"best1D":0.2941,"bestYACO":4.53,"bestYPRR":1.66,"bestTPRR":0.1915,"rank":null},{"pos":"RB","name":"Scottie Phillips","school":"Mississippi","conf":"SEC","cfr_id":"scottie-phillips-1","pfr_id":"PhilSc01","age":22.5836,"round":8.0,"years":2,"markers":4,"adjMarkers":-3.0,"grade":18.1818,"ath":0.5,"prod":0.2,"pff":3.0,"lastPPG":10.59,"bestPPG":17.9364,"wt":209.0,"ht":68.0,"bmi":31.7781,"dash":4.56,"wass":96.6756,"burst":108.0,"ypc":5.2878,"yptp":0.9511,"bestRec":10.0,"bestTotalYds":1033.0,"firstPPG":17.9364,"careerBA":0.0935,"careerMTF":0.1259,"career1D":0.3094,"careerYACO":3.0827,"careerYPRR":0.6408,"careerTPRR":0.0704,"bestBA":0.1111,"bestMTF":0.1307,"best1D":0.3791,"bestYACO":3.37,"bestYPRR":0.66,"bestTPRR":0.0794,"rank":null},{"pos":"RB","name":"LeVante Bellamy","school":"Western Michigan","conf":"MAC","cfr_id":"levante-bellamy-1","pfr_id":"BellLe02","age":23.4384,"round":8.0,"years":5,"markers":4,"adjMarkers":-3.0,"grade":18.1818,"ath":0.3333,"prod":0.6,"pff":7.0,"lastPPG":23.5154,"bestPPG":23.5154,"wt":192.0,"ht":69.0,"bmi":28.3532,"dash":4.5,"wass":93.6443,"burst":129.65,"ypc":6.0649,"yptp":0.8714,"bestRec":30.0,"bestTotalYds":581.0,"firstPPG":5.7,"careerBA":0.1011,"careerMTF":0.1729,"career1D":0.2806,"careerYACO":3.3948,"careerYPRR":0.7746,"careerTPRR":0.1516,"bestBA":0.1633,"bestMTF":0.2038,"best1D":0.5,"bestYACO":4.57,"bestYPRR":1.92,"bestTPRR":0.2857,"rank":null},{"pos":"RB","name":"Tony Jones Jr.","school":"Notre Dame","conf":"Ind","cfr_id":"tony-jones-jr-1","age":22.4493,"round":8.0,"years":3,"markers":3,"adjMarkers":-4.0,"grade":13.6364,"ath":0.5,"prod":0.0,"pff":2.0,"lastPPG":12.7583,"bestPPG":12.7583,"wt":220.0,"ht":70.0,"bmi":31.5664,"dash":4.68,"wass":91.7211,"burst":114.75,"ypc":5.4649,"yptp":0.6202,"bestRec":15.0,"bestTotalYds":549.0,"firstPPG":4.0333,"careerBA":0.0812,"careerMTF":0.1624,"career1D":0.2804,"careerYACO":3.2288,"careerYPRR":0.8248,"careerTPRR":0.1178,"bestBA":0.0903,"bestMTF":0.2292,"best1D":0.2892,"bestYACO":3.81,"bestYPRR":1.64,"bestTPRR":0.1394,"rank":null},{"pos":"RB","name":"Darius Anderson","school":"TCU","conf":"Big 12","cfr_id":"darius-anderson-1","age":22.6548,"round":8.0,"years":4,"markers":3,"adjMarkers":-4.0,"grade":13.6364,"ath":0.5,"prod":0.0,"pff":2.0,"lastPPG":12.7583,"bestPPG":12.7583,"wt":208.0,"ht":70.0,"bmi":29.8446,"dash":4.61,"wass":92.1064,"burst":125.2,"ypc":5.6233,"yptp":0.7112,"bestRec":22.0,"bestTotalYds":825.0,"firstPPG":3.2636,"careerBA":0.058,"careerMTF":0.2367,"career1D":0.2483,"careerYACO":3.3248,"careerYPRR":0.6179,"careerTPRR":0.129,"bestBA":0.0741,"bestMTF":0.281,"best1D":0.2963,"bestYACO":3.89,"bestYPRR":1.08,"bestTPRR":0.2414,"rank":null},{"pos":"RB","name":"Brian Herrien","school":"Georgia","conf":"SEC","cfr_id":"brian-herrien-1","age":22.2438,"round":8.0,"years":4,"markers":3,"adjMarkers":-4.0,"grade":13.6364,"ath":0.5,"prod":0.0,"pff":4.0,"lastPPG":9.8333,"bestPPG":9.8333,"wt":209.0,"ht":71.0,"bmi":29.1493,"dash":4.62,"wass":91.7505,"burst":128.45,"ypc":5.1011,"yptp":0.4288,"bestRec":16.0,"bestTotalYds":377.0,"firstPPG":4.8083,"careerBA":0.0616,"careerMTF":0.1522,"career1D":0.2717,"careerYACO":3.2681,"careerYPRR":0.9176,"careerTPRR":0.2033,"bestBA":0.1111,"bestMTF":0.1803,"best1D":0.3039,"bestYACO":3.48,"bestYPRR":1.25,"bestTPRR":0.2667,"rank":null},{"pos":"RB","name":"Sewo Olonilua","school":"TCU","conf":"Big 12","cfr_id":"sewo-olonilua-1","age":22.4411,"round":8.0,"years":4,"markers":3,"adjMarkers":-4.0,"grade":13.6364,"ath":0.5,"prod":0.0,"pff":5.0,"lastPPG":11.925,"bestPPG":11.925,"wt":232.0,"ht":75.0,"bmi":28.9977,"dash":4.66,"wass":98.3953,"burst":122.7,"ypc":4.6667,"yptp":0.5402,"bestRec":24.0,"bestTotalYds":496.0,"firstPPG":1.6846,"careerBA":0.0609,"careerMTF":0.1768,"career1D":0.3159,"careerYACO":3.1913,"careerYPRR":0.6879,"careerTPRR":0.1312,"bestBA":0.2,"bestMTF":0.2074,"best1D":0.4286,"bestYACO":4.73,"bestYPRR":1.51,"bestTPRR":0.1818,"rank":null},{"pos":"RB","name":"Patrick Taylor","school":"Memphis","conf":"American","cfr_id":"patrick-taylor-jr-1","pfr_id":"TaylPa01","age":22.0219,"round":8.0,"years":4,"markers":3,"adjMarkers":-4.0,"grade":13.6364,"ath":0.3333,"prod":0.2,"pff":3.0,"lastPPG":13.0333,"bestPPG":18.35,"wt":217.0,"ht":73.0,"bmi":28.6294,"dash":4.57,"wass":99.5004,"burst":119.3,"ypc":5.3806,"yptp":0.8574,"bestRec":19.0,"bestTotalYds":1014.0,"firstPPG":6.2538,"careerBA":0.0673,"careerMTF":0.1477,"career1D":0.2953,"careerYACO":3.2561,"careerYPRR":0.8543,"careerTPRR":0.1555,"bestBA":0.086,"bestMTF":0.1739,"best1D":0.3205,"bestYACO":4.33,"bestYPRR":1.13,"bestTPRR":0.1852,"rank":null},{"pos":"RB","name":"Javon Leake","school":"Maryland","conf":"Big Ten","cfr_id":"javon-leake-1","age":21.7671,"round":8.0,"years":3,"markers":3,"adjMarkers":-4.0,"grade":13.6364,"ath":0.5,"prod":0.2,"pff":7.0,"lastPPG":11.3417,"bestPPG":11.3417,"wt":215.0,"ht":73.0,"bmi":28.3656,"dash":4.65,"wass":91.9722,"burst":120.3,"ypc":7.8897,"yptp":0.5407,"bestRec":9.0,"bestTotalYds":313.0,"firstPPG":2.4333,"careerBA":0.1438,"careerMTF":0.2329,"career1D":0.2945,"careerYACO":4.0753,"careerYPRR":0.4565,"careerTPRR":0.0725,"bestBA":0.2222,"bestMTF":0.3107,"best1D":0.3824,"bestYACO":4.88,"bestYPRR":0.5,"bestTPRR":0.0763,"rank":null},{"pos":"RB","name":"J.J. Taylor","school":"Arizona","conf":"Pac-12","cfr_id":"jj-taylor-1","pfr_id":"TaylJJ01","age":23.3397,"round":8.0,"years":4,"markers":2,"adjMarkers":-5.0,"grade":9.0909,"ath":0.1667,"prod":0.2,"pff":7.0,"lastPPG":14.8182,"bestPPG":17.3917,"wt":185.0,"ht":65.0,"bmi":30.7853,"dash":4.61,"wass":81.9215,"burst":117.65,"ypc":5.5588,"yptp":1.0791,"bestRec":32.0,"bestTotalYds":896.0,"firstPPG":10.425,"careerBA":0.0771,"careerMTF":0.2175,"career1D":0.2774,"careerYACO":2.8887,"careerYPRR":0.8725,"careerTPRR":0.1436,"bestBA":0.1579,"bestMTF":0.2895,"best1D":0.4211,"bestYACO":4.68,"bestYPRR":1.58,"bestTPRR":0.227,"rank":null},{"pos":"RB","name":"Salvon Ahmed","school":"Washington","conf":"Pac-12","cfr_id":"salvon-ahmed-1","pfr_id":"AhmeSa01","age":23.2219,"round":8.0,"years":3,"markers":0,"adjMarkers":-7.0,"grade":0.0,"ath":0.0,"prod":0.0,"pff":3.0,"lastPPG":16.0333,"bestPPG":16.0333,"wt":197.0,"ht":71.0,"bmi":27.4757,"dash":4.62,"wass":86.4825,"burst":118.65,"ypc":5.711,"yptp":0.8941,"bestRec":21.0,"bestTotalYds":778.0,"firstPPG":5.9615,"careerBA":0.071,"careerMTF":0.1761,"career1D":0.2756,"careerYACO":3.3949,"careerYPRR":0.9218,"careerTPRR":0.1482,"bestBA":0.0984,"bestMTF":0.2131,"best1D":0.2981,"bestYACO":3.47,"bestYPRR":2.08,"bestTPRR":0.3514,"rank":null},{"pos":"RB","name":"Ty'Son Williams","school":"BYU","conf":"Ind","cfr_id":"tyson-williams-4","pfr_id":"WillTy01","age":23.6712,"round":8.0,"years":4,"markers":0,"adjMarkers":-7.0,"grade":0.0,"ath":0.0,"prod":0.0,"pff":2.0,"lastPPG":14.025,"bestPPG":14.025,"ypc":4.8069,"yptp":0.3848,"bestRec":12.0,"bestTotalYds":503.0,"firstPPG":1.1167,"careerBA":0.0641,"careerMTF":0.1581,"career1D":0.2564,"careerYACO":2.8632,"careerYPRR":0.8697,"careerTPRR":0.1379,"bestBA":0.08,"bestMTF":0.18,"best1D":0.28,"bestYACO":3.36,"bestYPRR":2.17,"bestTPRR":0.1667,"rank":null},{"pos":"WR","name":"CeeDee Lamb","school":"Oklahoma","conf":"Big 12","cfr_id":"ceedee-lamb-1","pfr_id":"LambCe00","age":21.0795,"round":1.0,"overall":17.0,"years":3,"markers":11,"adjMarkers":14.0,"grade":86.9565,"ath":0.6667,"prod":0.8571,"pff":15.0,"lastPPG":22.0538,"bestPPG":22.0538,"wt":198.0,"ht":74.0,"bmi":25.4215,"dash":4.5,"wass":96.5706,"burst":120.65,"boy20":2.0,"boy30":3.0,"boa20":19.4137,"boa30":20.4137,"firstYPTPA":1.8637,"lastYPTPA":3.4921,"bestYPTPA":3.4921,"firstMSYards":0.1593,"bestMSYards":0.3187,"careerYPRR":3.0472,"careerYPRRzone":3.5994,"careerTPRR":0.2266,"career1DRR":0.1193,"careerYACR":8.8208,"careerMTF":0.2486,"careerSlot":0.1827,"bestYPRR":3.991,"bestTPRR":0.2651,"best1DRR":0.1325,"bestYACR":11.0161,"rank":null},{"pos":"WR","name":"Justin Jefferson","school":"LSU","conf":"SEC","cfr_id":"justin-jefferson-1","pfr_id":"JeffJu00","age":20.8904,"round":1.0,"overall":22.0,"years":3,"markers":11,"adjMarkers":14.0,"grade":86.9565,"ath":0.8333,"prod":0.7143,"pff":8.0,"lastPPG":24.8667,"bestPPG":24.8667,"wt":202.0,"ht":73.0,"bmi":26.6504,"dash":4.43,"wass":104.8978,"burst":126.75,"boy20":2.0,"boy30":2.0,"boa20":19.2247,"boa30":19.2247,"firstYPTPA":0.0,"lastYPTPA":2.716,"bestYPTPA":2.716,"firstMSYards":0.0,"bestMSYards":0.2946,"careerYPRR":2.5664,"careerYPRRzone":3.0509,"careerTPRR":0.2338,"career1DRR":0.1148,"careerYACR":5.8242,"careerMTF":0.1818,"careerSlot":0.6872,"bestYPRR":2.6415,"bestTPRR":0.245,"best1DRR":0.1235,"bestYACR":6.4324,"rank":null},{"pos":"WR","name":"Jalen Reagor","school":"TCU","conf":"Big 12","cfr_id":"jalen-reagor-1","pfr_id":"ReagJa00","age":21.3425,"round":1.0,"overall":21.0,"years":3,"markers":10,"adjMarkers":13.0,"grade":82.6087,"ath":0.8333,"prod":0.5714,"pff":5.0,"lastPPG":11.9167,"bestPPG":20.0846,"wt":206.0,"ht":71.0,"bmi":28.7309,"dash":4.47,"wass":103.197,"burst":140.4,"boy20":1.0,"boy30":2.0,"boa20":18.6767,"boa30":19.6767,"firstYPTPA":1.3395,"lastYPTPA":1.5508,"bestYPTPA":2.5941,"firstMSYards":0.1671,"bestMSYards":0.386,"careerYPRR":2.0833,"careerYPRRzone":2.0595,"careerTPRR":0.2591,"career1DRR":0.0842,"careerYACR":5.6939,"careerMTF":0.1156,"careerSlot":0.1193,"bestYPRR":2.5616,"bestTPRR":0.3227,"best1DRR":0.1034,"bestYACR":7.5152,"rank":null},{"pos":"WR","name":"Brandon Aiyuk","school":"Arizona State","conf":"Pac-12","cfr_id":"brandon-aiyuk-1","pfr_id":"AiyuBr00","age":22.1397,"round":1.0,"overall":25.0,"years":2,"markers":10,"adjMarkers":13.0,"grade":82.6087,"ath":0.6667,"prod":0.7143,"pff":10.0,"lastPPG":19.4,"bestPPG":19.4,"wt":205.0,"ht":73.0,"bmi":27.0462,"dash":4.5,"wass":99.9848,"burst":132.0,"boy20":2.0,"boy30":2.0,"boa20":21.474,"boa30":21.474,"firstYPTPA":1.197,"lastYPTPA":3.1204,"bestYPTPA":3.1204,"firstMSYards":0.1567,"bestMSYards":0.3644,"careerYPRR":2.7267,"careerYPRRzone":2.9596,"careerTPRR":0.239,"career1DRR":0.0949,"careerYACR":9.8571,"careerMTF":0.2347,"careerSlot":0.1377,"bestYPRR":3.0408,"bestTPRR":0.2526,"best1DRR":0.102,"bestYACR":10.9231,"rank":null},{"pos":"WR","name":"Jerry Jeudy","school":"Alabama","conf":"SEC","cfr_id":"jerry-jeudy-1","pfr_id":"JeudJe00","age":21.0356,"round":1.0,"overall":15.0,"years":3,"markers":7,"adjMarkers":10.0,"grade":69.5652,"ath":0.5,"prod":0.4286,"pff":13.0,"lastPPG":19.4923,"bestPPG":19.4923,"wt":193.0,"ht":73.0,"bmi":25.463,"dash":4.45,"wass":98.4345,"burst":119.5,"boy20":2.0,"boa20":19.3699,"firstYPTPA":0.7952,"lastYPTPA":2.8645,"bestYPTPA":3.0023,"firstMSYards":0.0975,"bestMSYards":0.2709,"careerYPRR":2.9462,"careerYPRRzone":3.7026,"careerTPRR":0.2516,"career1DRR":0.1237,"careerYACR":7.3333,"careerMTF":0.2013,"careerSlot":0.677,"bestYPRR":3.3157,"bestTPRR":0.3068,"best1DRR":0.1506,"bestYACR":7.7532,"rank":null},{"pos":"WR","name":"Laviska Shenault Jr.","school":"Colorado","conf":"Pac-12","cfr_id":"laviska-shenault-jr-1","pfr_id":"ShenLa00","age":21.5863,"round":2.0,"overall":42.0,"years":3,"markers":8,"adjMarkers":9.0,"grade":68.1818,"ath":0.6667,"prod":0.4286,"pff":14.0,"lastPPG":16.7727,"bestPPG":29.4,"wt":227.0,"ht":73.0,"bmi":29.9488,"dash":4.58,"wass":103.1796,"boy20":2.0,"boy30":2.0,"boa20":19.9205,"boa30":19.9205,"firstYPTPA":0.4108,"lastYPTPA":1.8634,"bestYPTPA":2.4071,"firstMSYards":0.0538,"bestMSYards":0.3376,"careerYPRR":3.3872,"careerYPRRzone":2.6701,"careerTPRR":0.3438,"career1DRR":0.1458,"careerYACR":7.42,"careerMTF":0.3,"careerSlot":0.3544,"bestYPRR":7.0,"bestTPRR":0.4167,"best1DRR":0.2083,"bestYACR":7.5714,"rank":null},{"pos":"WR","name":"Michael Pittman Jr.","school":"USC","conf":"Pac-12","cfr_id":"michael-pittman-jr-1","pfr_id":"PittMi01","age":22.589,"round":2.0,"overall":34.0,"years":4,"markers":8,"adjMarkers":9.0,"grade":65.2174,"ath":0.8333,"prod":0.2857,"pff":4.0,"lastPPG":22.6538,"bestPPG":22.6538,"wt":223.0,"ht":76.0,"bmi":27.1442,"dash":4.52,"wass":106.8516,"burst":122.55,"boy20":3.0,"boy30":4.0,"boa20":20.9233,"boa30":21.9233,"firstYPTPA":0.1783,"lastYPTPA":2.4805,"bestYPTPA":2.4805,"firstMSYards":0.0227,"bestMSYards":0.2921,"careerYPRR":2.2204,"careerYPRRzone":2.5936,"careerTPRR":0.2248,"career1DRR":0.0912,"careerYACR":5.3158,"careerMTF":0.117,"careerSlot":0.1256,"bestYPRR":2.7333,"bestTPRR":0.2667,"best1DRR":0.1333,"bestYACR":6.7826,"rank":null},{"pos":"WR","name":"Devin Duvernay","school":"Texas","conf":"Big 12","cfr_id":"devin-duvernay-1","pfr_id":"DuveDe00","age":22.6493,"round":3.0,"overall":92.0,"years":4,"markers":9,"adjMarkers":9.0,"grade":65.2174,"ath":0.6667,"prod":0.7143,"pff":9.0,"lastPPG":23.6585,"bestPPG":23.6585,"wt":200.0,"ht":70.0,"bmi":28.6968,"dash":4.39,"wass":107.6966,"burst":121.85,"boy20":4.0,"boy30":4.0,"boa20":21.9836,"boa30":21.9836,"firstYPTPA":1.03,"lastYPTPA":2.9552,"bestYPTPA":2.9552,"firstMSYards":0.1362,"bestMSYards":0.3685,"careerYPRR":1.9496,"careerYPRRzone":1.8744,"careerTPRR":0.1923,"career1DRR":0.0914,"careerYACR":6.3714,"careerMTF":0.1886,"careerSlot":0.5393,"bestYPRR":3.0,"bestTPRR":0.278,"best1DRR":0.1466,"bestYACR":9.85,"rank":null},{"pos":"WR","name":"Gabriel Davis","school":"UCF","conf":"American","cfr_id":"gabriel-davis-1","pfr_id":"DaviGa01","age":21.0986,"round":4.0,"overall":128.0,"years":3,"markers":11,"adjMarkers":9.0,"grade":65.2174,"ath":1.0,"prod":0.7143,"pff":5.0,"lastPPG":22.3417,"bestPPG":22.3417,"wt":216.0,"ht":74.0,"bmi":27.7325,"dash":4.54,"wass":101.6858,"burst":121.5,"boy20":2.0,"boy30":3.0,"boa20":19.4329,"boa30":20.4329,"firstYPTPA":0.9222,"lastYPTPA":2.7155,"bestYPTPA":2.7155,"firstMSYards":0.0907,"bestMSYards":0.2996,"careerYPRR":2.3204,"careerYPRRzone":3.019,"careerTPRR":0.2445,"career1DRR":0.0948,"careerYACR":4.3618,"careerMTF":0.1118,"careerSlot":0.0823,"bestYPRR":2.9548,"bestTPRR":0.3048,"best1DRR":0.1167,"bestYACR":5.6296,"rank":null},{"pos":"WR","name":"Tyler Johnson","school":"Minnesota","conf":"Big Ten","cfr_id":"tyler-johnson-6","pfr_id":"JohnTy00","age":21.6986,"round":5.0,"overall":161.0,"years":4,"markers":10,"adjMarkers":7.0,"grade":65.0,"ath":0.5,"prod":1.0,"pff":9.0,"lastPPG":22.0636,"bestPPG":22.0636,"wt":206.0,"ht":73.0,"bmi":27.1782,"boy20":2.0,"boy30":2.0,"boa20":19.0329,"boa30":19.0329,"firstYPTPA":0.4365,"lastYPTPA":3.4379,"bestYPTPA":3.4379,"firstMSYards":0.0625,"bestMSYards":0.4475,"careerYPRR":3.049,"careerYPRRzone":4.1103,"careerTPRR":0.3117,"career1DRR":0.1452,"careerYACR":5.3645,"careerMTF":0.1262,"careerSlot":0.5908,"bestYPRR":3.6381,"bestTPRR":0.3631,"best1DRR":0.1758,"bestYACR":6.4286,"rank":null},{"pos":"WR","name":"Henry Ruggs III","school":"Alabama","conf":"SEC","cfr_id":"henry-ruggs-iii-1","pfr_id":"RuggHe00","age":21.2849,"round":1.0,"overall":12.0,"years":3,"markers":5,"adjMarkers":8.0,"grade":60.8696,"ath":0.6667,"prod":0.0,"pff":6.0,"lastPPG":14.175,"bestPPG":14.175,"wt":188.0,"ht":71.0,"bmi":26.2204,"dash":4.27,"wass":113.1036,"burst":136.9,"firstYPTPA":0.6898,"lastYPTPA":1.8374,"bestYPTPA":1.8374,"firstMSYards":0.0846,"bestMSYards":0.1677,"careerYPRR":2.2277,"careerYPRRzone":2.8059,"careerTPRR":0.1819,"career1DRR":0.0942,"careerYACR":8.9592,"careerMTF":0.1939,"careerSlot":0.2015,"bestYPRR":2.4624,"bestTPRR":0.1853,"best1DRR":0.0981,"bestYACR":10.475,"rank":null},{"pos":"WR","name":"Chase Claypool","school":"Notre Dame","conf":"Ind","cfr_id":"chase-claypool-1","pfr_id":"ClayCh01","age":21.8329,"round":2.0,"overall":49.0,"years":4,"markers":7,"adjMarkers":8.0,"grade":60.8696,"ath":1.0,"prod":0.0,"pff":4.0,"lastPPG":19.0538,"bestPPG":19.0538,"wt":238.0,"ht":76.0,"bmi":28.97,"dash":4.42,"wass":124.7148,"burst":131.85,"boy20":4.0,"boy30":4.0,"boa20":21.1671,"boa30":21.1671,"firstYPTPA":0.2093,"lastYPTPA":2.4928,"bestYPTPA":2.4928,"firstMSYards":0.0265,"bestMSYards":0.3073,"careerYPRR":1.8514,"careerYPRRzone":2.182,"careerTPRR":0.2007,"career1DRR":0.0888,"careerYACR":5.351,"careerMTF":0.1788,"careerSlot":0.1963,"bestYPRR":2.4809,"bestTPRR":0.2584,"best1DRR":0.122,"bestYACR":6.8333,"rank":null},{"pos":"WR","name":"Denzel Mims","school":"Baylor","conf":"Big 12","cfr_id":"denzel-mims-1","pfr_id":"MimsDe00","age":22.5726,"round":2.0,"overall":59.0,"years":4,"markers":7,"adjMarkers":8.0,"grade":60.8696,"ath":0.6667,"prod":0.2857,"pff":2.0,"lastPPG":17.1429,"bestPPG":18.0917,"wt":207.0,"ht":75.0,"bmi":25.873,"dash":4.38,"wass":112.4874,"burst":130.95,"boy20":2.0,"boy30":2.0,"boa20":19.9068,"boa30":19.9068,"firstYPTPA":0.0501,"lastYPTPA":2.2973,"bestYPTPA":2.3528,"firstMSYards":0.0066,"bestMSYards":0.3149,"careerYPRR":2.1114,"careerYPRRzone":1.9943,"careerTPRR":0.2357,"career1DRR":0.0976,"careerYACR":4.3817,"careerMTF":0.1344,"careerSlot":0.0412,"bestYPRR":2.3605,"bestTPRR":0.2628,"best1DRR":0.1186,"bestYACR":6.8852,"rank":null},{"pos":"WR","name":"Antonio Gandy-Golden","school":"Liberty","conf":"Ind","cfr_id":"antonio-gandy-golden-1","pfr_id":"GandAn00","age":22.0712,"round":4.0,"overall":142.0,"years":2,"markers":10,"adjMarkers":8.0,"grade":60.8696,"ath":0.5,"prod":1.0,"pff":8.0,"lastPPG":21.4308,"bestPPG":21.4308,"wt":223.0,"ht":76.0,"bmi":27.1442,"dash":4.6,"wass":99.6101,"burst":124.7,"boy20":1.0,"boy30":1.0,"boa20":20.4055,"boa30":20.4055,"firstYPTPA":2.3147,"lastYPTPA":3.0953,"bestYPTPA":3.0953,"firstMSYards":0.3305,"bestMSYards":0.3598,"careerYPRR":2.687,"careerTPRR":0.2919,"career1DRR":0.1243,"careerYACR":5.4832,"careerMTF":0.2215,"careerSlot":0.0888,"bestYPRR":2.9473,"bestTPRR":0.2927,"best1DRR":0.1287,"bestYACR":5.9747,"rank":null},{"pos":"WR","name":"Tee Higgins","school":"Clemson","conf":"ACC","cfr_id":"tee-higgins-1","pfr_id":"HiggTe00","age":21.2986,"round":2.0,"overall":33.0,"years":3,"markers":4,"adjMarkers":5.0,"grade":55.0,"ath":0.3333,"prod":0.1429,"pff":11.0,"lastPPG":17.5533,"bestPPG":17.5533,"wt":216.0,"ht":76.0,"bmi":26.2921,"boy20":2.0,"boa20":19.6329,"firstYPTPA":0.7356,"lastYPTPA":2.3018,"bestYPTPA":2.3018,"firstMSYards":0.1046,"bestMSYards":0.2698,"careerYPRR":3.3719,"careerYPRRzone":3.1481,"careerTPRR":0.2948,"career1DRR":0.1405,"careerYACR":5.9259,"careerMTF":0.2074,"careerSlot":0.1207,"bestYPRR":3.7097,"bestTPRR":0.3548,"best1DRR":0.1509,"bestYACR":7.5882,"rank":null},{"pos":"WR","name":"KJ Hamler","school":"Penn State","conf":"Big Ten","cfr_id":"kj-hamler-1","pfr_id":"HamlKJ00","age":20.8301,"round":2.0,"overall":46.0,"years":2,"markers":4,"adjMarkers":5.0,"grade":55.0,"ath":0.1667,"prod":0.2857,"pff":4.0,"lastPPG":15.2846,"bestPPG":15.2846,"wt":178.0,"ht":69.0,"bmi":26.2858,"boy20":1.0,"boy30":2.0,"boa20":19.1644,"boa30":20.1644,"firstYPTPA":1.9894,"lastYPTPA":2.4632,"bestYPTPA":2.4632,"firstMSYards":0.266,"bestMSYards":0.3142,"careerYPRR":2.2328,"careerYPRRzone":1.9605,"careerTPRR":0.2234,"career1DRR":0.0929,"careerYACR":7.5306,"careerMTF":0.0816,"careerSlot":0.9332,"bestYPRR":2.4835,"bestTPRR":0.2527,"best1DRR":0.1044,"bestYACR":8.6429,"rank":null},{"pos":"WR","name":"Isaiah Hodgins","school":"Oregon State","conf":"Pac-12","cfr_id":"isaiah-hodgins-1","pfr_id":"HodgIs00","age":21.5425,"round":6.0,"overall":207.0,"years":3,"markers":9,"adjMarkers":5.0,"grade":47.8261,"ath":0.5,"prod":0.8571,"pff":8.0,"lastPPG":23.425,"bestPPG":23.425,"wt":210.0,"ht":76.0,"bmi":25.5618,"dash":4.61,"wass":92.992,"burst":124.05,"boy20":2.0,"boy30":3.0,"boa20":19.8767,"boa30":20.8767,"firstYPTPA":0.7618,"lastYPTPA":2.7947,"bestYPTPA":2.7947,"firstMSYards":0.1168,"bestMSYards":0.3826,"careerYPRR":2.1087,"careerYPRRzone":2.5756,"careerTPRR":0.2274,"career1DRR":0.1114,"careerYACR":3.1648,"careerMTF":0.0625,"careerSlot":0.0733,"bestYPRR":2.6744,"bestTPRR":0.2725,"best1DRR":0.1455,"bestYACR":3.7458,"rank":null},{"pos":"WR","name":"Van Jefferson","school":"Florida","conf":"SEC","cfr_id":"van-jefferson-1","pfr_id":"JeffVa00","age":23.7808,"round":2.0,"overall":57.0,"years":4,"markers":2,"adjMarkers":3.0,"grade":45.0,"ath":0.1667,"prod":0.0,"pff":2.0,"lastPPG":11.6462,"bestPPG":11.6462,"wt":200.0,"ht":73.0,"bmi":26.3866,"firstYPTPA":1.1242,"lastYPTPA":1.4099,"bestYPTPA":1.4099,"firstMSYards":0.1437,"bestMSYards":0.1812,"careerYPRR":1.6333,"careerYPRRzone":1.9834,"careerTPRR":0.1977,"career1DRR":0.0818,"careerYACR":4.5,"careerMTF":0.0977,"careerSlot":0.5567,"bestYPRR":1.997,"bestTPRR":0.2193,"best1DRR":0.0973,"bestYACR":5.4286,"rank":null},{"pos":"WR","name":"Bryan Edwards","school":"South Carolina","conf":"SEC","cfr_id":"bryan-edwards-1","pfr_id":"EdwaBr01","age":21.4795,"round":3.0,"overall":81.0,"years":4,"markers":3,"adjMarkers":3.0,"grade":45.0,"ath":0.3333,"prod":0.1429,"pff":6.0,"lastPPG":19.08,"bestPPG":19.08,"wt":212.0,"ht":75.0,"bmi":26.4979,"boy20":1.0,"boy30":4.0,"boa20":17.8137,"boa30":20.8137,"firstYPTPA":1.4677,"lastYPTPA":1.7548,"bestYPTPA":2.0076,"firstMSYards":0.2129,"bestMSYards":0.306,"careerYPRR":2.0053,"careerYPRRzone":2.7797,"careerTPRR":0.2444,"career1DRR":0.0885,"careerYACR":6.1368,"careerMTF":0.188,"careerSlot":0.1271,"bestYPRR":2.5823,"bestTPRR":0.3386,"best1DRR":0.1139,"bestYACR":7.6056,"rank":null},{"pos":"WR","name":"Quez Watkins","school":"Southern Mississippi","conf":"CUSA","cfr_id":"quez-watkins-1","pfr_id":"WatkQu00","age":21.9096,"round":6.0,"overall":200.0,"years":3,"markers":8,"adjMarkers":4.0,"grade":43.4783,"ath":0.8333,"prod":0.4286,"pff":9.0,"lastPPG":18.1583,"bestPPG":19.6364,"wt":185.0,"ht":73.0,"bmi":24.4076,"dash":4.35,"wass":103.3343,"burst":124.55,"boy20":2.0,"boy30":2.0,"boa20":20.2438,"boa30":20.2438,"firstYPTPA":0.7677,"lastYPTPA":2.6895,"bestYPTPA":2.6895,"firstMSYards":0.108,"bestMSYards":0.3169,"careerYPRR":2.462,"careerYPRRzone":2.644,"careerTPRR":0.2587,"career1DRR":0.0996,"careerYACR":7.8165,"careerMTF":0.1519,"careerSlot":0.1344,"bestYPRR":3.0284,"bestTPRR":0.2751,"best1DRR":0.1105,"bestYACR":8.8889,"rank":null},{"pos":"WR","name":"Isaiah Coulter","school":"Rhode Island","conf":"FCS","pfr_id":"CoulIs00","age":21.6329,"round":5.0,"overall":171.0,"markers":5,"adjMarkers":2.0,"grade":42.1053,"ath":0.8333,"prod":0.0,"pff":5.0,"wt":198.0,"ht":74.0,"bmi":25.63,"dash":4.45,"wass":100.9846,"burst":121.7,"careerYPRR":2.1412,"careerYPRRzone":3.1,"careerTPRR":0.249,"career1DRR":0.0882,"careerYACR":4.9028,"careerMTF":0.0972,"careerSlot":0.0457,"bestYPRR":4.0,"bestTPRR":0.25,"best1DRR":0.0887,"bestYACR":58.0,"rank":null},{"pos":"WR","name":"Darnell Mooney","school":"Tulane","conf":"American","cfr_id":"darnell-mooney-1","pfr_id":"MoonDa00","age":22.5205,"round":5.0,"overall":173.0,"years":4,"markers":6,"adjMarkers":3.0,"grade":39.1304,"ath":0.3333,"prod":0.5714,"pff":9.0,"lastPPG":11.4846,"bestPPG":15.0692,"wt":176.0,"ht":70.0,"bmi":25.2531,"dash":4.38,"wass":95.6415,"burst":124.9,"boy20":2.0,"boy30":2.0,"boa20":19.8548,"boa30":19.8548,"firstYPTPA":1.0349,"lastYPTPA":2.122,"bestYPTPA":3.3434,"firstMSYards":0.1963,"bestMSYards":0.4176,"careerYPRR":2.2783,"careerYPRRzone":2.6322,"careerTPRR":0.2509,"career1DRR":0.0954,"careerYACR":5.2338,"careerMTF":0.1623,"careerSlot":0.345,"bestYPRR":2.9582,"bestTPRR":0.3171,"best1DRR":0.1134,"bestYACR":8.3125,"rank":null},{"pos":"WR","name":"Donovan Peoples-Jones","school":"Michigan","conf":"Big Ten","cfr_id":"donovan-peoples-jones-1","pfr_id":"PeopDo00","age":21.211,"round":6.0,"overall":187.0,"years":3,"markers":7,"adjMarkers":3.0,"grade":39.1304,"ath":1.0,"prod":0.1429,"pff":0.0,"lastPPG":10.2818,"bestPPG":12.3,"wt":212.0,"ht":74.0,"bmi":27.2189,"dash":4.48,"wass":105.2577,"burst":145.15,"boy20":2.0,"boa20":19.5452,"firstYPTPA":0.8006,"lastYPTPA":1.0709,"bestYPTPA":1.7637,"firstMSYards":0.1244,"bestMSYards":0.2183,"careerYPRR":1.6968,"careerYPRRzone":1.9859,"careerTPRR":0.2255,"career1DRR":0.0841,"careerYACR":5.6078,"careerMTF":0.1176,"careerSlot":0.3402,"bestYPRR":2.0676,"bestTPRR":0.2365,"best1DRR":0.1014,"bestYACR":6.8636,"rank":null},{"pos":"WR","name":"James Proche","school":"SMU","conf":"American","cfr_id":"james-proche-1","pfr_id":"ProcJa00","age":23.6247,"round":6.0,"overall":201.0,"years":4,"markers":5,"adjMarkers":1.0,"grade":35.0,"ath":0.1667,"prod":0.5714,"pff":7.0,"lastPPG":25.0231,"bestPPG":25.0231,"wt":201.0,"ht":71.0,"bmi":28.0336,"boy20":1.0,"boy30":3.0,"boa20":19.9589,"boa30":21.9589,"firstYPTPA":1.5548,"lastYPTPA":2.4306,"bestYPTPA":2.5511,"firstMSYards":0.2238,"bestMSYards":0.3432,"careerYPRR":2.5682,"careerYPRRzone":2.8057,"careerTPRR":0.2961,"career1DRR":0.1149,"careerYACR":5.6424,"careerMTF":0.1424,"careerSlot":0.5651,"bestYPRR":2.6605,"bestTPRR":0.3403,"best1DRR":0.1294,"bestYACR":8.425,"rank":null},{"pos":"WR","name":"Joe Reed","school":"Virginia","conf":"ACC","cfr_id":"joe-reed-4","pfr_id":"ReedJo03","age":22.337,"round":5.0,"overall":151.0,"years":4,"markers":5,"adjMarkers":2.0,"grade":34.7826,"ath":0.8333,"prod":0.0,"pff":7.0,"lastPPG":14.7,"bestPPG":14.7,"wt":224.0,"ht":73.0,"bmi":29.553,"dash":4.47,"wass":112.2142,"burst":126.1,"boy20":3.0,"boa20":20.6712,"firstYPTPA":0.1594,"lastYPTPA":1.3083,"bestYPTPA":1.3083,"firstMSYards":0.0268,"bestMSYards":0.1812,"careerYPRR":1.5967,"careerYPRRzone":1.643,"careerTPRR":0.2011,"career1DRR":0.075,"careerYACR":7.2308,"careerMTF":0.2231,"careerSlot":0.7214,"bestYPRR":2.75,"bestTPRR":0.2483,"best1DRR":0.1071,"bestYACR":11.56,"rank":null},{"pos":"WR","name":"Dezmon Patmon","school":"Washington State","conf":"Pac-12","cfr_id":"dezmon-patmon-1","pfr_id":"PatmDe00","age":21.7507,"round":6.0,"overall":329.0,"years":4,"markers":6,"adjMarkers":2.0,"grade":34.7826,"ath":1.0,"prod":0.0,"pff":6.0,"lastPPG":14.0154,"bestPPG":14.0154,"wt":225.0,"ht":76.0,"bmi":27.3876,"dash":4.48,"wass":111.7122,"burst":127.2,"firstYPTPA":0.0287,"lastYPTPA":1.0763,"bestYPTPA":1.2053,"firstMSYards":0.004,"bestMSYards":0.1679,"careerYPRR":1.8967,"careerYPRRzone":2.3783,"careerTPRR":0.2143,"career1DRR":0.0956,"careerYACR":4.6859,"careerMTF":0.1282,"careerSlot":0.0224,"bestYPRR":2.2295,"bestTPRR":0.2594,"best1DRR":0.1153,"bestYACR":5.1186,"rank":null},{"pos":"WR","name":"Omar Bayless","school":"Arkansas State","conf":"Sun Belt","cfr_id":"omar-bayless-1","age":23.3918,"round":8.0,"years":4,"markers":8,"adjMarkers":2.0,"grade":34.7826,"ath":0.5,"prod":0.7143,"pff":5.0,"lastPPG":27.8292,"bestPPG":27.8292,"wt":212.0,"ht":73.0,"bmi":27.9698,"dash":4.62,"wass":93.0675,"burst":122.7,"boy20":4.0,"boy30":4.0,"boa20":22.726,"boa30":22.726,"firstYPTPA":0.2918,"lastYPTPA":3.5245,"bestYPTPA":3.5245,"firstMSYards":0.0359,"bestMSYards":0.4074,"careerYPRR":2.1399,"careerYPRRzone":2.7509,"careerTPRR":0.2179,"career1DRR":0.0958,"careerYACR":5.7006,"careerMTF":0.1412,"careerSlot":0.1212,"bestYPRR":3.1208,"bestTPRR":0.266,"best1DRR":0.1283,"bestYACR":6.5806,"rank":null},{"pos":"WR","name":"Quintez Cephus","school":"Wisconsin","conf":"Big Ten","cfr_id":"quintez-cephus-1","pfr_id":"CephQu00","age":22.0986,"round":5.0,"overall":166.0,"years":3,"markers":4,"adjMarkers":1.0,"grade":30.4348,"ath":0.3333,"prod":0.2857,"pff":10.0,"lastPPG":13.65,"bestPPG":13.65,"wt":202.0,"ht":73.0,"bmi":26.6504,"dash":4.73,"wass":80.7118,"burst":127.45,"boy20":2.0,"boy30":4.0,"boa20":20.4329,"boa30":22.4356,"firstYPTPA":0.291,"lastYPTPA":2.5743,"bestYPTPA":2.5743,"firstMSYards":0.0375,"bestMSYards":0.3169,"careerYPRR":2.9683,"careerYPRRzone":3.3095,"careerTPRR":0.2679,"career1DRR":0.1409,"careerYACR":5.2151,"careerMTF":0.1505,"careerSlot":0.2529,"bestYPRR":3.34,"bestTPRR":0.3127,"best1DRR":0.1733,"bestYACR":6.1333,"rank":null},{"pos":"WR","name":"John Hightower","school":"Boise State","conf":"MWC","cfr_id":"john-hightower-1","pfr_id":"HighJo00","age":23.9342,"round":5.0,"overall":168.0,"years":2,"markers":4,"adjMarkers":1.0,"grade":30.4348,"ath":0.5,"prod":0.1429,"pff":9.0,"lastPPG":14.9186,"bestPPG":14.9186,"wt":189.0,"ht":73.0,"bmi":24.9353,"dash":4.43,"wass":98.147,"burst":126.45,"boy20":2.0,"boa20":23.2685,"firstYPTPA":1.0957,"lastYPTPA":2.0367,"bestYPTPA":2.0367,"firstMSYards":0.1328,"bestMSYards":0.2574,"careerYPRR":2.8262,"careerYPRRzone":2.8622,"careerTPRR":0.2637,"career1DRR":0.0918,"careerYACR":6.7561,"careerMTF":0.1098,"careerSlot":0.0931,"bestYPRR":3.8182,"bestTPRR":0.3485,"best1DRR":0.1288,"bestYACR":6.9032,"rank":null},{"pos":"WR","name":"K.J. Osborn","school":"Miami (FL)","conf":"ACC","cfr_id":"kj-osborn-1","pfr_id":"OsboKJ00","age":22.9068,"round":5.0,"overall":176.0,"years":4,"markers":4,"adjMarkers":1.0,"grade":30.4348,"ath":0.6667,"prod":0.0,"pff":2.0,"lastPPG":10.4769,"bestPPG":13.2714,"wt":203.0,"ht":71.0,"bmi":28.3125,"dash":4.48,"wass":100.7892,"burst":125.25,"boy20":3.0,"boa20":21.2411,"firstYPTPA":0.2645,"lastYPTPA":1.2546,"bestYPTPA":2.1289,"firstMSYards":0.0436,"bestMSYards":0.2827,"careerYPRR":1.6686,"careerYPRRzone":2.0608,"careerTPRR":0.2136,"career1DRR":0.0777,"careerYACR":5.1027,"careerMTF":0.1849,"careerSlot":0.4132,"bestYPRR":2.2356,"bestTPRR":0.2682,"best1DRR":0.0877,"bestYACR":6.6981,"rank":null},{"pos":"WR","name":"Freddie Swain","school":"Florida","conf":"SEC","cfr_id":"freddie-swain-1","pfr_id":"SwaiFr00","age":21.7562,"round":6.0,"overall":214.0,"years":4,"markers":4,"adjMarkers":0.0,"grade":26.087,"ath":0.6667,"prod":0.0,"pff":4.0,"lastPPG":11.2,"bestPPG":11.2,"wt":197.0,"ht":73.0,"bmi":25.9908,"dash":4.46,"wass":99.5765,"burst":124.05,"firstYPTPA":0.2878,"lastYPTPA":1.1094,"bestYPTPA":1.1094,"firstMSYards":0.0421,"bestMSYards":0.1322,"careerYPRR":1.5962,"careerYPRRzone":3.0515,"careerTPRR":0.1843,"career1DRR":0.0833,"careerYACR":6.8824,"careerMTF":0.1471,"careerSlot":0.7336,"bestYPRR":2.3288,"bestTPRR":0.2432,"best1DRR":0.1261,"bestYACR":8.4286,"rank":null},{"pos":"WR","name":"Tyrie Cleveland","school":"Florida","conf":"SEC","cfr_id":"tyrie-cleveland-1","pfr_id":"ClevTy00","age":22.6301,"round":7.0,"overall":252.0,"years":4,"markers":5,"adjMarkers":0.0,"grade":26.087,"ath":0.6667,"prod":0.1429,"pff":4.0,"lastPPG":5.0846,"bestPPG":7.56,"wt":209.0,"ht":74.0,"bmi":26.8338,"dash":4.46,"wass":105.6421,"burst":130.15,"boy20":2.0,"boa20":19.9644,"firstYPTPA":0.7268,"lastYPTPA":0.7532,"bestYPTPA":1.3141,"firstMSYards":0.1062,"bestMSYards":0.2076,"careerYPRR":1.6571,"careerYPRRzone":1.7613,"careerTPRR":0.163,"career1DRR":0.0639,"careerYACR":5.2405,"careerMTF":0.1266,"careerSlot":0.1867,"bestYPRR":2.0812,"bestTPRR":0.1827,"best1DRR":0.0781,"bestYACR":7.2143,"rank":null},{"pos":"WR","name":"Marquez Callaway","school":"Tennessee","conf":"SEC","cfr_id":"marquez-callaway-1","pfr_id":"CallMa01","age":22.1123,"round":8.0,"years":4,"markers":6,"adjMarkers":0.0,"grade":26.087,"ath":0.6667,"prod":0.2857,"pff":4.0,"lastPPG":9.9615,"bestPPG":9.9615,"wt":205.0,"ht":73.0,"bmi":27.0462,"dash":4.55,"wass":95.6617,"burst":127.6,"boy20":2.0,"boy30":2.0,"boa20":19.4466,"boa30":19.4466,"firstYPTPA":0.0346,"lastYPTPA":1.7639,"bestYPTPA":1.9933,"firstMSYards":0.0042,"bestMSYards":0.2512,"careerYPRR":1.9029,"careerYPRRzone":2.2059,"careerTPRR":0.1896,"career1DRR":0.0855,"careerYACR":4.7391,"careerMTF":0.1739,"careerSlot":0.1308,"bestYPRR":2.0845,"bestTPRR":0.2308,"best1DRR":0.1056,"bestYACR":5.5,"rank":null},{"pos":"WR","name":"Stephen Guidry","school":"Mississippi State","conf":"SEC","cfr_id":"stephen-guidry-1","age":23.1123,"round":8.0,"years":2,"markers":5,"adjMarkers":-1.0,"grade":21.7391,"ath":0.6667,"prod":0.1429,"pff":5.0,"lastPPG":8.225,"bestPPG":8.225,"wt":201.0,"ht":75.0,"bmi":25.123,"dash":4.47,"wass":100.6922,"burst":120.3,"boy20":2.0,"boa20":22.4466,"firstYPTPA":1.3622,"lastYPTPA":1.2286,"bestYPTPA":1.3622,"firstMSYards":0.1948,"bestMSYards":0.1948,"careerYPRR":1.6019,"careerYPRRzone":1.8706,"careerTPRR":0.2,"career1DRR":0.0718,"careerYACR":6.4898,"careerMTF":0.3265,"careerSlot":0.0538,"bestYPRR":1.7323,"bestTPRR":0.2031,"best1DRR":0.0843,"bestYACR":9.1053,"rank":null},{"pos":"WR","name":"Collin Johnson","school":"Texas","conf":"Big 12","cfr_id":"collin-johnson-2","pfr_id":"JohnCo01","age":22.6192,"round":5.0,"overall":165.0,"years":4,"markers":1,"adjMarkers":-2.0,"grade":20.0,"ath":0.1667,"prod":0.0,"pff":3.0,"lastPPG":15.9857,"bestPPG":16.0385,"wt":222.0,"ht":78.0,"bmi":25.6544,"boy20":3.0,"boa20":20.9534,"firstYPTPA":0.7875,"lastYPTPA":1.1919,"bestYPTPA":2.0693,"firstMSYards":0.1042,"bestMSYards":0.2725,"careerYPRR":1.8386,"careerYPRRzone":1.7981,"careerTPRR":0.2147,"career1DRR":0.0933,"careerYACR":3.8351,"careerMTF":0.1223,"careerSlot":0.1079,"bestYPRR":2.0632,"bestTPRR":0.2189,"best1DRR":0.1152,"bestYACR":4.6852,"rank":null},{"pos":"WR","name":"Jauan Jennings","school":"Tennessee","conf":"SEC","cfr_id":"jauan-jennings-1","pfr_id":"JennJa00","age":22.8274,"round":7.0,"overall":217.0,"years":5,"markers":3,"adjMarkers":-2.0,"grade":17.3913,"ath":0.1667,"prod":0.2857,"pff":10.0,"lastPPG":16.5385,"bestPPG":16.5385,"wt":215.0,"ht":75.0,"bmi":26.8729,"dash":4.72,"wass":86.6364,"burst":108.8,"boy20":2.0,"boy30":5.0,"boa20":19.1616,"boa30":22.1616,"firstYPTPA":0.4027,"lastYPTPA":2.6917,"bestYPTPA":2.6917,"firstMSYards":0.0575,"bestMSYards":0.3367,"careerYPRR":2.117,"careerYPRRzone":2.3615,"careerTPRR":0.2242,"career1DRR":0.0934,"careerYACR":7.0,"careerMTF":0.3493,"careerSlot":0.5783,"bestYPRR":3.086,"bestTPRR":0.5,"best1DRR":0.1667,"bestYACR":8.0339,"rank":null},{"pos":"WR","name":"Kalija Lipscomb","school":"Vanderbilt","conf":"SEC","cfr_id":"kalija-lipscomb-1","age":22.5836,"round":8.0,"years":4,"markers":4,"adjMarkers":-2.0,"grade":17.3913,"ath":0.3333,"prod":0.2857,"pff":7.0,"lastPPG":11.0273,"bestPPG":18.9308,"wt":207.0,"ht":73.0,"bmi":27.3101,"dash":4.57,"wass":94.9152,"burst":117.9,"boy20":2.0,"boy30":3.0,"boa20":19.9178,"boa30":20.9178,"firstYPTPA":0.8179,"lastYPTPA":1.3412,"bestYPTPA":2.2179,"firstMSYards":0.1283,"bestMSYards":0.2891,"careerYPRR":2.0531,"careerYPRRzone":2.017,"careerTPRR":0.2857,"career1DRR":0.0967,"careerYACR":4.9239,"careerMTF":0.2081,"careerSlot":0.2106,"bestYPRR":2.8618,"bestTPRR":0.3324,"best1DRR":0.1287,"bestYACR":6.6316,"rank":null},{"pos":"WR","name":"Trishton Jackson","school":"Syracuse","conf":"ACC","cfr_id":"trishton-jackson-1","pfr_id":"JackTr02","age":22.1616,"round":8.0,"years":4,"markers":4,"adjMarkers":-2.0,"grade":17.3913,"ath":0.3333,"prod":0.2857,"pff":4.0,"lastPPG":19.55,"bestPPG":19.55,"wt":197.0,"ht":73.0,"bmi":25.9908,"dash":4.5,"wass":96.0829,"burst":119.7,"boy20":4.0,"boy30":4.0,"boa20":21.4959,"boa30":21.4959,"firstYPTPA":0.2412,"lastYPTPA":2.5074,"bestYPTPA":2.5074,"firstMSYards":0.0334,"bestMSYards":0.3543,"careerYPRR":1.8103,"careerYPRRzone":2.2962,"careerTPRR":0.2055,"career1DRR":0.0761,"careerYACR":5.1529,"careerMTF":0.1529,"careerSlot":0.2221,"bestYPRR":2.0769,"bestTPRR":0.2308,"best1DRR":0.0818,"bestYACR":8.8,"rank":null},{"pos":"WR","name":"Kendrick Rogers","school":"Texas A&M","conf":"SEC","cfr_id":"kendrick-rogers-1","age":22.7479,"round":8.0,"years":3,"markers":4,"adjMarkers":-2.0,"grade":17.3913,"ath":0.6667,"prod":0.0,"pff":3.0,"lastPPG":5.9308,"bestPPG":7.55,"wt":208.0,"ht":76.0,"bmi":25.3183,"dash":4.51,"wass":100.5512,"burst":122.35,"firstYPTPA":0.2205,"lastYPTPA":0.7765,"bestYPTPA":0.7765,"firstMSYards":0.0303,"bestMSYards":0.1147,"careerYPRR":1.2167,"careerYPRRzone":1.5714,"careerTPRR":0.1904,"career1DRR":0.0635,"careerYACR":3.2059,"careerMTF":0.1765,"careerSlot":0.1766,"bestYPRR":1.5701,"bestTPRR":0.2676,"best1DRR":0.0888,"bestYACR":3.8182,"rank":null},{"pos":"WR","name":"Aaron Parker","school":"Rhode Island","conf":"FCS","age":21.9616,"round":8.0,"markers":3,"adjMarkers":-3.0,"grade":15.7895,"ath":0.5,"prod":0.0,"pff":6.0,"wt":209.0,"ht":73.5,"bmi":27.2,"dash":4.57,"wass":95.8322,"burst":101.05,"careerYPRR":2.3939,"careerYPRRzone":3.5444,"careerTPRR":0.2986,"career1DRR":0.1133,"careerYACR":5.044,"careerMTF":0.1758,"careerSlot":0.5383,"bestYPRR":2.46,"bestTPRR":0.4,"best1DRR":0.1165,"bestYACR":5.4,"rank":null},{"pos":"WR","name":"Quartney Davis","school":"Texas A&M","conf":"SEC","cfr_id":"quartney-davis-1","age":22.0822,"round":8.0,"years":2,"markers":3,"adjMarkers":-3.0,"grade":13.6364,"ath":0.3333,"prod":0.1429,"pff":0.0,"lastPPG":12.9818,"bestPPG":12.9818,"wt":201.0,"ht":73.0,"bmi":26.5185,"dash":4.54,"wass":94.6243,"boy20":1.0,"boa20":20.4164,"firstYPTPA":1.3356,"lastYPTPA":1.3628,"bestYPTPA":1.3628,"firstMSYards":0.1781,"bestMSYards":0.2013,"careerYPRR":1.4784,"careerYPRRzone":1.6959,"careerTPRR":0.2133,"career1DRR":0.0789,"careerYACR":4.2525,"careerMTF":0.1111,"careerSlot":0.5573,"bestYPRR":1.6211,"bestTPRR":0.2447,"best1DRR":0.0895,"bestYACR":4.8704,"rank":null},{"pos":"WR","name":"Binjimen Victor","school":"Ohio State","conf":"Big Ten","cfr_id":"binjimen-victor-1","age":21.3068,"round":8.0,"years":4,"markers":3,"adjMarkers":-3.0,"grade":13.0435,"ath":0.5,"prod":0.0,"pff":7.0,"lastPPG":8.8929,"bestPPG":8.8929,"wt":198.0,"ht":76.0,"bmi":24.1011,"dash":4.6,"wass":88.4431,"burst":123.5,"firstYPTPA":0.1572,"lastYPTPA":1.349,"bestYPTPA":1.349,"firstMSYards":0.023,"bestMSYards":0.1479,"careerYPRR":1.7092,"careerYPRRzone":2.0491,"careerTPRR":0.1849,"career1DRR":0.0855,"careerYACR":4.2289,"careerMTF":0.2169,"careerSlot":0.1242,"bestYPRR":2.4076,"bestTPRR":0.2143,"best1DRR":0.1176,"bestYACR":4.8286,"rank":null},{"pos":"WR","name":"Darrell Stewart Jr.","school":"Michigan State","conf":"Big Ten","cfr_id":"darrell-stewart-jr-1","age":23.8137,"round":8.0,"years":4,"markers":2,"adjMarkers":-4.0,"grade":9.5238,"ath":0.3333,"prod":0.0,"pff":4.0,"lastPPG":15.7867,"bestPPG":15.7867,"wt":212.0,"ht":73.0,"bmi":27.9698,"burst":118.0,"boy20":4.0,"boa20":23.1479,"firstYPTPA":0.0786,"lastYPTPA":1.5054,"bestYPTPA":1.5054,"firstMSYards":0.0109,"bestMSYards":0.219,"careerYPRR":1.7128,"careerYPRRzone":1.8652,"careerTPRR":0.2706,"career1DRR":0.0895,"careerYACR":4.5229,"careerMTF":0.2157,"careerSlot":0.5971,"bestYPRR":2.6298,"bestTPRR":0.3321,"best1DRR":0.1183,"bestYACR":5.7885,"rank":null},{"pos":"WR","name":"K.J. Hill","school":"Ohio State","conf":"Big Ten","cfr_id":"kj-hill-1","pfr_id":"HillKJ00","age":22.6411,"round":7.0,"overall":220.0,"years":4,"markers":1,"adjMarkers":-4.0,"grade":8.6957,"ath":0.1667,"prod":0.0,"pff":6.0,"lastPPG":12.9071,"bestPPG":13.8714,"wt":196.0,"ht":73.0,"bmi":25.8588,"dash":4.6,"wass":87.5497,"burst":112.25,"firstYPTPA":0.6437,"lastYPTPA":1.5743,"bestYPTPA":1.5775,"firstMSYards":0.0942,"bestMSYards":0.1735,"careerYPRR":2.1897,"careerYPRRzone":2.2639,"careerTPRR":0.2498,"career1DRR":0.1117,"careerYACR":6.2239,"careerMTF":0.1642,"careerSlot":0.9489,"bestYPRR":2.7315,"bestTPRR":0.3025,"best1DRR":0.1327,"bestYACR":7.7,"rank":null},{"pos":"WR","name":"Austin Mack","school":"Ohio State","conf":"Big Ten","cfr_id":"austin-mack-1","pfr_id":"MackAu01","age":22.6822,"round":8.0,"years":4,"markers":2,"adjMarkers":-4.0,"grade":8.6957,"ath":0.3333,"prod":0.0,"pff":4.0,"lastPPG":7.3727,"bestPPG":8.1375,"wt":208.0,"ht":73.0,"bmi":27.442,"dash":4.59,"wass":93.7222,"burst":112.05,"firstYPTPA":0.0369,"lastYPTPA":0.8936,"bestYPTPA":0.8936,"firstMSYards":0.0054,"bestMSYards":0.098,"careerYPRR":1.6204,"careerYPRRzone":2.2648,"careerTPRR":0.1914,"career1DRR":0.0849,"careerYACR":2.6329,"careerMTF":0.1013,"careerSlot":0.1074,"bestYPRR":2.0168,"bestTPRR":0.2234,"best1DRR":0.1117,"bestYACR":3.0,"rank":null},{"pos":"WR","name":"Nick Westbrook-Ikhine","school":"Indiana","conf":"Big Ten","cfr_id":"nick-westbrook-1","pfr_id":"WestNi00","age":23.1288,"round":8.0,"years":4,"markers":1,"adjMarkers":-5.0,"grade":5.5556,"ath":0.0,"prod":0.1429,"pff":5.0,"lastPPG":9.9385,"bestPPG":15.0615,"boy20":2.0,"boa20":20.463,"firstYPTPA":0.1497,"lastYPTPA":1.2119,"bestYPTPA":2.182,"firstMSYards":0.0181,"bestMSYards":0.2796,"careerYPRR":1.6978,"careerYPRRzone":1.2865,"careerTPRR":0.1821,"career1DRR":0.0727,"careerYACR":4.0278,"careerMTF":0.1042,"careerSlot":0.1493,"bestYPRR":3.0521,"bestTPRR":0.2945,"best1DRR":0.1196,"bestYACR":5.0741,"rank":null},{"pos":"WR","name":"Lawrence Cager","school":"Georgia","conf":"SEC","cfr_id":"lawrence-cager-1","pfr_id":"CageLa01","age":22.7123,"round":8.0,"years":4,"markers":1,"adjMarkers":-5.0,"grade":5.0,"ath":0.1667,"prod":0.0,"pff":7.0,"lastPPG":11.6222,"bestPPG":11.6222,"wt":220.0,"ht":77.0,"bmi":26.088,"boy20":4.0,"boa20":22.0466,"firstYPTPA":0.1559,"lastYPTPA":1.1498,"bestYPTPA":1.1498,"firstMSYards":0.0194,"bestMSYards":0.17,"careerYPRR":1.7773,"careerYPRRzone":1.9745,"careerTPRR":0.2028,"career1DRR":0.0937,"careerYACR":3.2179,"careerMTF":0.0385,"careerSlot":0.0794,"bestYPRR":3.3287,"bestTPRR":0.2797,"best1DRR":0.1608,"bestYACR":3.5455,"rank":null},{"pos":"WR","name":"Chris Finke","school":"Notre Dame","conf":"Ind","cfr_id":"chris-finke-1","age":24.0137,"round":8.0,"years":4,"markers":1,"adjMarkers":-5.0,"grade":4.5455,"ath":0.1667,"prod":0.0,"pff":4.0,"lastPPG":8.5231,"bestPPG":9.2385,"wt":186.0,"ht":69.0,"bmi":27.4671,"dash":4.57,"wass":85.2861,"firstYPTPA":0.3152,"lastYPTPA":1.0962,"bestYPTPA":1.366,"firstMSYards":0.04,"bestMSYards":0.1629,"careerYPRR":1.3778,"careerYPRRzone":1.7946,"careerTPRR":0.163,"career1DRR":0.0716,"careerYACR":5.0,"careerMTF":0.1509,"careerSlot":0.7616,"bestYPRR":1.6712,"bestTPRR":0.1972,"best1DRR":0.0959,"bestYACR":5.8,"rank":null},{"pos":"WR","name":"Tony Brown","school":"Colorado","conf":"Pac-12","cfr_id":"tony-brown-9","age":22.7452,"round":8.0,"years":4,"markers":1,"adjMarkers":-5.0,"grade":4.3478,"ath":0.1667,"prod":0.0,"pff":6.0,"lastPPG":13.8333,"bestPPG":13.8333,"wt":198.0,"ht":73.0,"bmi":26.1227,"dash":4.65,"wass":84.7,"burst":116.45,"boy20":5.0,"boa20":23.0822,"firstYPTPA":0.4039,"lastYPTPA":1.7244,"bestYPTPA":1.7244,"firstMSYards":0.0495,"bestMSYards":0.2474,"careerYPRR":1.197,"careerYPRRzone":1.2746,"careerTPRR":0.1479,"career1DRR":0.0507,"careerYACR":5.4783,"careerMTF":0.1217,"careerSlot":0.0448,"bestYPRR":1.8853,"bestTPRR":0.1973,"best1DRR":0.088,"bestYACR":10.2143,"rank":null},{"pos":"WR","name":"Earnest Edwards","school":"Maine","conf":"FCS","age":22.1041,"round":8.0,"markers":0,"adjMarkers":-6.0,"grade":0.0,"ath":0.0,"prod":0.0,"pff":10.0,"wt":188.0,"ht":70.0,"bmi":26.57,"careerYPRR":3.4421,"careerYPRRzone":2.5,"careerTPRR":0.247,"career1DRR":0.1311,"careerYACR":9.32,"careerMTF":0.36,"careerSlot":0.3531,"bestYPRR":3.57,"bestTPRR":0.2475,"best1DRR":0.1353,"bestYACR":16.0,"rank":null},{"pos":"WR","name":"Aaron Fuller","school":"Washington","conf":"Pac-12","cfr_id":"aaron-fuller-1","age":22.6,"round":8.0,"years":4,"markers":0,"adjMarkers":-6.0,"grade":0.0,"ath":0.0,"prod":0.0,"pff":2.0,"lastPPG":12.7077,"bestPPG":12.7077,"wt":188.0,"ht":71.0,"bmi":26.2204,"dash":4.59,"wass":84.7105,"burst":116.8,"boy20":4.0,"boa20":21.9342,"firstYPTPA":0.451,"lastYPTPA":1.7122,"bestYPTPA":2.158,"firstMSYards":0.0508,"bestMSYards":0.2283,"careerYPRR":1.7557,"careerYPRRzone":2.1071,"careerTPRR":0.2255,"career1DRR":0.0843,"careerYACR":4.6273,"careerMTF":0.0994,"careerSlot":0.5109,"bestYPRR":2.2468,"bestTPRR":0.2676,"best1DRR":0.1028,"bestYACR":5.7797,"rank":null},{"pos":"TE","name":"Cole Kmet","school":"Notre Dame","conf":"Ind","cfr_id":"cole-kmet-1","pfr_id":"KmetCo00","age":21.1589,"round":2.0,"overall":43.0,"years":3,"markers":7,"adjMarkers":8.0,"grade":60.8696,"ath":1.0,"prod":0.125,"pff":2.0,"lastPPG":11.8636,"bestPPG":11.8636,"wt":262.0,"ht":78.0,"bmi":30.2738,"dash":4.7,"wass":107.3841,"burst":124.4,"boy15":3.0,"firstYPTPA":0.0399,"lastYPTPA":1.238,"bestYPTPA":1.238,"bestMSYards":0.1526,"careerYPG":19.7429,"careerYPRR":1.464,"careerTPRR":0.1737,"career1DRR":0.0678,"careerYACR":4.7333,"careerMTF":0.1,"careerSlot":0.2869,"avgPassBlock":68.6333,"avgRunBlock":64.1667,"bestYPRR":1.5512,"bestTPRR":0.25,"best1DRR":0.0723,"bestYACR":4.9535,"rank":null},{"pos":"TE","name":"Devin Asiasi","school":"UCLA","conf":"Pac-12","cfr_id":"devin-asiasi-1","pfr_id":"AsiaDe00","age":22.7315,"round":3.0,"overall":91.0,"years":3,"markers":8,"adjMarkers":8.0,"grade":60.8696,"ath":0.4,"prod":0.625,"pff":5.0,"lastPPG":11.0083,"bestPPG":11.0083,"wt":257.0,"ht":75.0,"bmi":32.1193,"dash":4.73,"wass":102.6877,"burst":109.35,"boy15":4.0,"boy20":3.0,"boa20":22.0658,"firstYPTPA":0.0486,"lastYPTPA":1.5047,"bestYPTPA":1.5047,"bestMSYards":0.2091,"careerYPG":23.2059,"careerYPRR":1.6302,"careerTPRR":0.1756,"career1DRR":0.0785,"careerYACR":6.0962,"careerMTF":0.1538,"careerSlot":0.3724,"avgPassBlock":67.2,"avgRunBlock":70.3333,"bestYPRR":1.9403,"bestTPRR":0.194,"best1DRR":0.0861,"bestYACR":9.6667,"rank":null},{"pos":"TE","name":"Harrison Bryant","school":"Florida Atlantic","conf":"CUSA","cfr_id":"harrison-bryant-1","pfr_id":"BryaHa00","age":22.0384,"round":4.0,"overall":115.0,"years":4,"markers":9,"adjMarkers":7.0,"grade":56.5217,"ath":0.2,"prod":1.0,"pff":10.0,"lastPPG":15.9538,"bestPPG":15.9538,"wt":243.0,"ht":77.0,"bmi":28.8124,"dash":4.73,"wass":97.0938,"burst":110.25,"boy15":2.0,"boy20":3.0,"boa20":20.3726,"firstYPTPA":0.1731,"lastYPTPA":2.0,"bestYPTPA":2.0,"bestMSYards":0.2538,"careerYPG":44.5208,"careerYPRR":2.5865,"careerTPRR":0.2503,"career1DRR":0.1294,"careerYACR":7.5676,"careerMTF":0.1554,"careerSlot":0.3895,"avgPassBlock":78.125,"avgRunBlock":71.075,"bestYPRR":3.0424,"bestTPRR":0.2848,"best1DRR":0.1606,"bestYACR":10.0227,"rank":null},{"pos":"TE","name":"Brycen Hopkins","school":"Purdue","conf":"Big Ten","cfr_id":"brycen-hopkins-1","pfr_id":"HopkBr01","age":23.1123,"round":4.0,"overall":136.0,"years":4,"markers":8,"adjMarkers":6.0,"grade":52.1739,"ath":0.6,"prod":0.625,"pff":4.0,"lastPPG":15.5,"bestPPG":15.5,"wt":245.0,"ht":76.0,"bmi":29.8191,"dash":4.66,"wass":103.9088,"burst":114.95,"boy15":4.0,"boy20":4.0,"boa20":22.4466,"firstYPTPA":0.3291,"lastYPTPA":1.6023,"bestYPTPA":1.6023,"bestMSYards":0.2232,"careerYPG":40.5208,"careerYPRR":1.7191,"careerTPRR":0.1908,"career1DRR":0.076,"careerYACR":7.0308,"careerMTF":0.0769,"careerSlot":0.5486,"avgPassBlock":68.175,"avgRunBlock":56.025,"bestYPRR":1.963,"bestTPRR":0.2017,"best1DRR":0.0859,"bestYACR":8.7,"rank":null},{"pos":"TE","name":"Albert Okwuegbunam","school":"Missouri","conf":"SEC","cfr_id":"albert-okwuegbunam-1","pfr_id":"OkwuAl00","age":22.0329,"round":4.0,"overall":118.0,"years":3,"markers":7,"adjMarkers":5.0,"grade":50.0,"ath":0.8,"prod":0.375,"pff":8.0,"lastPPG":8.4182,"bestPPG":13.9556,"wt":258.0,"ht":77.0,"bmi":30.591,"dash":4.49,"wass":126.9592,"boy15":1.0,"boy20":3.0,"boa20":21.3671,"firstYPTPA":0.9674,"lastYPTPA":0.8138,"bestYPTPA":1.0333,"bestMSYards":0.115,"careerYPG":35.9697,"careerYPRR":1.9966,"careerTPRR":0.2365,"career1DRR":0.1115,"careerYACR":5.5,"careerMTF":0.1224,"careerSlot":0.4425,"avgPassBlock":68.7667,"avgRunBlock":63.8333,"bestYPRR":2.5247,"bestTPRR":0.2814,"best1DRR":0.1543,"bestYACR":7.2069,"rank":null},{"pos":"TE","name":"Dalton Keene","school":"Virginia Tech","conf":"ACC","cfr_id":"dalton-keene-1","pfr_id":"KeenDa00","age":21.063,"round":3.0,"overall":101.0,"years":3,"markers":5,"adjMarkers":5.0,"grade":47.8261,"ath":0.8,"prod":0.0,"pff":4.0,"lastPPG":6.0231,"bestPPG":6.675,"wt":253.0,"ht":76.0,"bmi":30.7928,"dash":4.71,"wass":102.8175,"burst":120.3,"firstYPTPA":0.4073,"lastYPTPA":0.7547,"bestYPTPA":0.7967,"bestMSYards":0.1033,"careerYPG":19.6842,"careerYPRR":1.283,"careerTPRR":0.1218,"career1DRR":0.0617,"careerYACR":9.7458,"careerMTF":0.1525,"careerSlot":0.2972,"avgPassBlock":69.4,"avgRunBlock":60.1667,"bestYPRR":1.3586,"bestTPRR":0.1405,"best1DRR":0.0703,"bestYACR":10.4286,"rank":null},{"pos":"TE","name":"Jared Pinkney","school":"Vanderbilt","conf":"SEC","cfr_id":"jared-pinkney-1","age":22.7096,"round":8.0,"years":4,"markers":8,"adjMarkers":2.0,"grade":36.3636,"ath":0.4,"prod":0.75,"pff":4.0,"lastPPG":5.0273,"bestPPG":13.0308,"wt":257.0,"ht":76.0,"bmi":31.2796,"dash":4.96,"wass":84.9252,"boy15":1.0,"boy20":3.0,"boa20":21.0438,"firstYPTPA":0.7026,"lastYPTPA":0.6115,"bestYPTPA":1.8741,"bestMSYards":0.2443,"careerYPG":31.8367,"careerYPRR":1.4665,"careerTPRR":0.197,"career1DRR":0.0688,"careerYACR":6.2544,"careerMTF":0.1842,"careerSlot":0.3921,"avgPassBlock":60.85,"avgRunBlock":55.86,"bestYPRR":2.2781,"bestTPRR":1.0,"best1DRR":0.1036,"bestYACR":6.8636,"rank":null},{"pos":"TE","name":"Jacob Breeland","school":"Oregon","conf":"Pac-12","cfr_id":"jacob-breeland-1","age":23.6274,"round":8.0,"years":4,"markers":7,"adjMarkers":1.0,"grade":35.0,"ath":0.4,"prod":0.625,"pff":6.0,"lastPPG":17.0833,"bestPPG":17.0833,"wt":252.0,"ht":77.0,"bmi":29.8796,"boy15":2.0,"boy20":2.0,"boa20":20.9616,"firstYPTPA":0.3083,"lastYPTPA":0.9122,"bestYPTPA":1.0289,"bestMSYards":0.1284,"careerYPG":29.878,"careerYPRR":1.8533,"careerTPRR":0.1604,"career1DRR":0.0726,"careerYACR":6.9865,"careerMTF":0.1622,"careerSlot":0.4048,"avgPassBlock":71.725,"avgRunBlock":56.975,"bestYPRR":2.8125,"bestTPRR":0.2222,"best1DRR":0.1181,"bestYACR":14.0,"rank":null},{"pos":"TE","name":"Colby Parkinson","school":"Stanford","conf":"Pac-12","cfr_id":"colby-parkinson-1","pfr_id":"ParkCo02","age":21.326,"round":4.0,"overall":133.0,"years":3,"markers":4,"adjMarkers":2.0,"grade":34.7826,"ath":0.4,"prod":0.25,"pff":0.0,"lastPPG":9.7683,"bestPPG":9.7683,"wt":252.0,"ht":79.0,"bmi":28.3858,"dash":4.77,"wass":97.3547,"burst":109.75,"boy15":2.0,"firstYPTPA":0.2672,"lastYPTPA":1.3356,"bestYPTPA":1.3356,"bestMSYards":0.187,"careerYPG":30.0256,"careerYPRR":1.3616,"careerTPRR":0.1919,"career1DRR":0.0698,"careerYACR":3.9195,"careerMTF":0.046,"careerSlot":0.6254,"avgPassBlock":70.2,"avgRunBlock":63.7,"bestYPRR":1.4392,"bestTPRR":0.2353,"best1DRR":0.0882,"bestYACR":5.3103,"rank":null},{"pos":"TE","name":"Adam Trautman","school":"Dayton","conf":"FCS","pfr_id":"TrauAd00","age":23.2493,"round":4.0,"overall":105.0,"markers":2,"adjMarkers":0.0,"grade":33.3333,"ath":0.4,"prod":0.0,"wt":255.0,"ht":77.0,"bmi":30.2353,"dash":4.8,"wass":96.0739,"burst":115.65,"rank":null},{"pos":"TE","name":"Josiah Deguara","school":"Cincinnati","conf":"American","cfr_id":"josiah-deguara-1","pfr_id":"DeguJo00","age":23.2247,"round":3.0,"overall":94.0,"years":4,"markers":1,"adjMarkers":1.0,"grade":30.4348,"ath":0.0,"prod":0.0,"pff":5.0,"lastPPG":9.8286,"bestPPG":9.8286,"wt":242.0,"ht":74.0,"bmi":31.0676,"dash":4.72,"wass":97.5163,"burst":117.85,"boy15":3.0,"boy20":4.0,"boa20":22.5589,"firstYPTPA":0.1038,"lastYPTPA":1.3404,"bestYPTPA":1.3404,"bestMSYards":0.1975,"careerYPG":24.2826,"careerYPRR":1.4893,"careerTPRR":0.2013,"career1DRR":0.0707,"careerYACR":5.6522,"careerMTF":0.087,"careerSlot":0.5966,"avgPassBlock":65.25,"avgRunBlock":69.775,"bestYPRR":5.2222,"bestTPRR":0.4444,"best1DRR":0.1111,"bestYACR":5.9231,"rank":null},{"pos":"TE","name":"Stephen Sullivan","school":"LSU","conf":"SEC","cfr_id":"stephen-sullivan-1","pfr_id":"SullSt00","age":23.4384,"round":7.0,"overall":251.0,"years":3,"markers":5,"adjMarkers":0.0,"grade":26.087,"ath":0.8,"prod":0.125,"pff":0.0,"lastPPG":1.6667,"bestPPG":5.6385,"wt":248.0,"ht":77.0,"bmi":29.4053,"dash":4.66,"wass":105.1812,"burst":123.55,"firstYPTPA":0.73,"lastYPTPA":0.2293,"bestYPTPA":0.938,"bestMSYards":0.1222,"careerYPG":17.3659,"careerYPRR":1.4501,"careerTPRR":0.167,"career1DRR":0.0692,"careerYACR":3.6739,"careerMTF":0.0217,"careerSlot":0.2844,"avgPassBlock":51.1,"avgRunBlock":58.575,"bestYPRR":1.9206,"bestTPRR":0.2328,"best1DRR":0.0899,"bestYACR":5.0909,"rank":null},{"pos":"TE","name":"Hunter Bryant","school":"Washington","conf":"Pac-12","cfr_id":"hunter-bryant-2","pfr_id":"BryaHu02","age":21.7123,"round":8.0,"years":3,"markers":6,"adjMarkers":0.0,"grade":26.087,"ath":0.0,"prod":0.75,"pff":10.0,"lastPPG":12.675,"bestPPG":12.675,"wt":248.0,"ht":74.0,"bmi":31.8378,"dash":4.74,"wass":98.2581,"burst":112.75,"boy15":3.0,"boy20":3.0,"boa20":21.0466,"firstYPTPA":0.9511,"lastYPTPA":2.0122,"bestYPTPA":2.0122,"bestMSYards":0.2607,"careerYPG":53.6154,"careerYPRR":2.8981,"careerTPRR":0.2495,"career1DRR":0.1206,"careerYACR":7.6353,"careerMTF":0.2118,"careerSlot":0.557,"avgPassBlock":56.3333,"avgRunBlock":57.4333,"bestYPRR":3.4493,"bestTPRR":0.2632,"best1DRR":0.1481,"bestYACR":7.8182,"rank":null},{"pos":"TE","name":"Giovanni Ricci","school":"Western Michigan","conf":"MAC","cfr_id":"giovanni-ricci-1","pfr_id":"RiccGi00","age":23.5562,"round":8.0,"years":3,"markers":4,"adjMarkers":-2.0,"grade":22.2222,"ath":0.0,"prod":0.5,"pff":4.0,"lastPPG":12.5538,"bestPPG":12.5538,"boy15":3.0,"boy20":3.0,"boa20":22.8904,"firstYPTPA":0.2051,"lastYPTPA":1.5545,"bestYPTPA":1.5545,"bestMSYards":0.2052,"careerYPG":34.8125,"careerYPRR":1.6354,"careerTPRR":0.232,"career1DRR":0.0836,"careerYACR":4.5876,"careerMTF":0.0825,"careerSlot":0.4174,"avgPassBlock":70.2,"avgRunBlock":60.55,"bestYPRR":1.8136,"bestTPRR":0.2599,"best1DRR":0.096,"bestYACR":4.902,"rank":null},{"pos":"TE","name":"CJ O'Grady","school":"Arkansas","conf":"SEC","cfr_id":"cj-ogrady-1","age":23.6274,"round":8.0,"years":4,"markers":4,"adjMarkers":-2.0,"grade":17.3913,"ath":0.4,"prod":0.25,"pff":9.0,"lastPPG":12.6429,"bestPPG":12.6429,"wt":253.0,"ht":76.0,"bmi":30.7928,"dash":4.81,"wass":94.5301,"burst":117.3,"boy15":3.0,"boy20":3.0,"boa20":21.9616,"firstYPTPA":0.1552,"lastYPTPA":0.9163,"bestYPTPA":1.084,"bestMSYards":0.1734,"careerYPG":27.6286,"careerYPRR":1.7392,"careerTPRR":0.2428,"career1DRR":0.0953,"careerYACR":6.3103,"careerMTF":0.1954,"careerSlot":0.3729,"avgPassBlock":52.3,"avgRunBlock":52.525,"bestYPRR":4.5,"bestTPRR":0.4286,"best1DRR":0.1429,"bestYACR":8.6667,"rank":null},{"pos":"TE","name":"Tyler Davis","school":"Georgia Tech","conf":"ACC","cfr_id":"tyler-davis-2","pfr_id":"DaviTy02","age":23.0959,"round":6.0,"overall":206.0,"years":4,"markers":1,"adjMarkers":-3.0,"grade":16.6667,"ath":0.0,"prod":0.125,"pff":1.0,"lastPPG":3.15,"bestPPG":6.8617,"boy15":3.0,"boy20":3.0,"boa20":21.4301,"firstYPTPA":0.2816,"lastYPTPA":0.5502,"bestYPTPA":0.6791,"bestMSYards":0.1104,"careerYPG":14.087,"careerYPRR":1.1335,"careerTPRR":0.1744,"career1DRR":0.0641,"careerYACR":4.3594,"careerMTF":0.0,"careerSlot":0.3888,"avgPassBlock":57.55,"avgRunBlock":50.025,"bestYPRR":1.6596,"bestTPRR":0.2128,"best1DRR":0.0897,"bestYACR":7.5,"rank":null},{"pos":"TE","name":"Sean McKeon","school":"Michigan","conf":"Big Ten","cfr_id":"sean-mckeon-1","pfr_id":"McKeSe01","age":22.3562,"round":8.0,"years":4,"markers":3,"adjMarkers":-3.0,"grade":15.0,"ath":0.2,"prod":0.25,"pff":3.0,"lastPPG":4.85,"bestPPG":6.0846,"wt":242.0,"ht":77.0,"bmi":28.6939,"boy15":2.0,"boy20":2.0,"boa20":19.6904,"firstYPTPA":0.027,"lastYPTPA":0.5746,"bestYPTPA":0.8699,"bestMSYards":0.1352,"careerYPG":16.7,"careerYPRR":1.3077,"careerTPRR":0.1953,"career1DRR":0.0631,"careerYACR":5.7167,"careerMTF":0.0667,"careerSlot":0.1934,"avgPassBlock":64.425,"avgRunBlock":66.925,"bestYPRR":2.0,"bestTPRR":0.4,"best1DRR":0.0733,"bestYACR":7.0714,"rank":null},{"pos":"TE","name":"Charlie Woerner","school":"Georgia","conf":"SEC","cfr_id":"charlie-woerner-1","pfr_id":"WoerCh00","age":22.5562,"round":6.0,"overall":190.0,"years":4,"markers":1,"adjMarkers":-3.0,"grade":13.0435,"ath":0.2,"prod":0.0,"pff":2.0,"lastPPG":1.6286,"bestPPG":1.8429,"wt":244.0,"ht":77.0,"bmi":28.931,"dash":4.78,"wass":93.4777,"burst":118.65,"firstYPTPA":0.1299,"lastYPTPA":0.1884,"bestYPTPA":0.4157,"bestMSYards":0.0468,"careerYPG":7.0943,"careerYPRR":0.785,"careerTPRR":0.1232,"career1DRR":0.0355,"careerYACR":5.1176,"careerMTF":0.1176,"careerSlot":0.452,"avgPassBlock":64.55,"avgRunBlock":71.25,"bestYPRR":1.3333,"bestTPRR":0.2,"best1DRR":0.0541,"bestYACR":7.7778,"rank":null},{"pos":"TE","name":"Dominick Wood-Anderson","school":"Tennessee","conf":"SEC","cfr_id":"dominick-wood-anderson-1","age":22.2575,"round":8.0,"years":2,"markers":2,"adjMarkers":-4.0,"grade":8.6957,"ath":0.4,"prod":0.0,"pff":0.0,"lastPPG":4.1769,"bestPPG":4.1769,"wt":261.0,"ht":76.0,"bmi":31.7664,"dash":4.92,"wass":89.0861,"burst":119.0,"firstYPTPA":0.4714,"lastYPTPA":0.7444,"bestYPTPA":0.7444,"bestMSYards":0.0931,"careerYPG":17.0,"careerYPRR":1.0938,"careerTPRR":0.1796,"career1DRR":0.059,"careerYACR":4.1053,"careerMTF":0.0263,"careerSlot":0.3643,"avgPassBlock":58.9,"avgRunBlock":61.85,"bestYPRR":1.2823,"bestTPRR":0.1962,"best1DRR":0.0671,"bestYACR":5.1905,"rank":null},{"pos":"TE","name":"Joey Magnifico","school":"Memphis","conf":"American","cfr_id":"joey-magnifico-1","age":22.9205,"round":8.0,"years":4,"markers":1,"adjMarkers":-5.0,"grade":5.5556,"ath":0.0,"prod":0.125,"pff":6.0,"lastPPG":5.0385,"bestPPG":6.2357,"firstYPTPA":0.1782,"lastYPTPA":0.7631,"bestYPTPA":0.8789,"bestMSYards":0.1066,"careerYPG":20.0566,"careerYPRR":1.5057,"careerTPRR":0.1501,"career1DRR":0.0807,"careerYACR":6.5634,"careerMTF":0.2113,"careerSlot":0.2444,"avgPassBlock":74.125,"avgRunBlock":65.2,"bestYPRR":1.7794,"bestTPRR":0.197,"best1DRR":0.1212,"bestYACR":10.0,"rank":null},{"pos":"TE","name":"Gabe Nabers","school":"Florida State","conf":"ACC","cfr_id":"gabe-nabers-1","round":8.0,"years":3,"markers":1,"adjMarkers":-5.0,"grade":5.5556,"ath":0.0,"prod":0.125,"pff":5.0,"lastPPG":3.7769,"bestPPG":3.7769,"firstYPTPA":0.0058,"lastYPTPA":0.5116,"bestYPTPA":0.5116,"bestMSYards":0.0629,"careerYPG":7.0789,"careerYPRR":1.3927,"careerTPRR":0.1309,"career1DRR":0.0681,"careerYACR":9.2105,"careerMTF":0.1053,"careerSlot":0.2846,"avgPassBlock":42.4667,"avgRunBlock":50.0333,"bestYPRR":1.8475,"bestTPRR":0.25,"best1DRR":0.125,"bestYACR":10.8,"rank":null},{"pos":"TE","name":"Nate Wieting","school":"Iowa","conf":"Big Ten","cfr_id":"nate-wieting-1","age":23.2082,"round":8.0,"years":3,"markers":1,"adjMarkers":-5.0,"grade":5.5556,"ath":0.0,"prod":0.125,"pff":4.0,"lastPPG":1.9727,"bestPPG":1.9727,"firstYPTPA":0.0479,"lastYPTPA":0.2854,"bestYPTPA":0.2854,"bestMSYards":0.0393,"careerYPG":6.3793,"careerYPRR":0.6607,"careerTPRR":0.0964,"career1DRR":0.0321,"careerYACR":6.6154,"careerMTF":0.0769,"careerSlot":0.1927,"avgPassBlock":58.425,"avgRunBlock":61.05,"bestYPRR":2.8333,"bestTPRR":0.2308,"best1DRR":0.1667,"bestYACR":18.5,"rank":null},{"pos":"TE","name":"Charlie Taumoepeau","school":"Portland State","conf":"FCS","age":22.1178,"round":8.0,"markers":1,"adjMarkers":-5.0,"grade":5.5556,"ath":0.2,"prod":0.0,"wt":240.0,"ht":74.25,"bmi":30.6037,"dash":4.75,"wass":94.2903,"burst":122.55,"rank":null},{"pos":"TE","name":"Thaddeus Moss","school":"LSU","conf":"SEC","cfr_id":"thaddeus-moss-1","pfr_id":"MossTh01","age":21.9808,"round":8.0,"years":2,"markers":1,"adjMarkers":-5.0,"grade":5.0,"ath":0.2,"prod":0.0,"pff":0.0,"lastPPG":9.1429,"bestPPG":9.1429,"wt":250.0,"ht":74.0,"bmi":32.0946,"firstYPTPA":0.1119,"lastYPTPA":1.0053,"bestYPTPA":1.0053,"bestMSYards":0.0946,"careerYPG":22.9259,"careerYPRR":1.1484,"careerTPRR":0.1317,"career1DRR":0.0538,"careerYACR":5.434,"careerMTF":0.0755,"careerSlot":0.2219,"avgPassBlock":61.35,"avgRunBlock":67.35,"bestYPRR":1.2102,"bestTPRR":0.2059,"best1DRR":0.0588,"bestYACR":5.4468,"rank":null},{"pos":"TE","name":"Mitchell Wilcox","school":"South Florida","conf":"American","cfr_id":"mitchell-wilcox-1","pfr_id":"WilcMi01","age":23.4959,"round":8.0,"years":4,"markers":1,"adjMarkers":-5.0,"grade":4.3478,"ath":0.0,"prod":0.125,"pff":2.0,"lastPPG":7.75,"bestPPG":9.0833,"wt":247.0,"ht":75.0,"bmi":30.8695,"dash":4.88,"wass":87.1059,"burst":108.7,"boy15":4.0,"boy20":4.0,"boa20":22.8301,"firstYPTPA":0.7765,"lastYPTPA":1.0671,"bestYPTPA":1.2587,"bestMSYards":0.1683,"careerYPG":27.0612,"careerYPRR":1.5131,"careerTPRR":0.1771,"career1DRR":0.072,"careerYACR":4.1,"careerMTF":0.11,"careerSlot":0.4537,"avgPassBlock":65.975,"avgRunBlock":61.475,"bestYPRR":1.8815,"bestTPRR":0.2195,"best1DRR":0.101,"bestYACR":9.3333,"rank":null},{"pos":"TE","name":"Kyle Markway","school":"South Carolina","conf":"SEC","cfr_id":"kyle-markway-1","age":23.1753,"round":8.0,"years":3,"markers":0,"adjMarkers":-6.0,"grade":0.0,"ath":0.0,"prod":0.0,"pff":3.0,"lastPPG":6.4917,"bestPPG":6.4917,"firstYPTPA":0.1633,"lastYPTPA":0.7505,"bestYPTPA":0.7505,"bestMSYards":0.1309,"careerYPG":12.4054,"careerYPRR":1.106,"careerTPRR":0.1422,"career1DRR":0.053,"careerYACR":5.0,"careerMTF":0.0541,"careerSlot":0.4757,"avgPassBlock":45.0667,"avgRunBlock":57.5667,"bestYPRR":2.5909,"bestTPRR":0.1458,"best1DRR":0.1364,"bestYACR":7.6667,"rank":null},{"pos":"TE","name":"Tommy Hudson","school":"Arizona State","conf":"Pac-12","cfr_id":"tommy-hudson-1","pfr_id":"HudsTo00","round":8.0,"years":3,"markers":0,"adjMarkers":-6.0,"grade":0.0,"ath":0.0,"prod":0.0,"pff":3.0,"lastPPG":1.6308,"bestPPG":1.6308,"firstYPTPA":0.0649,"lastYPTPA":0.2932,"bestYPTPA":0.2932,"bestMSYards":0.0342,"careerYPG":5.2564,"careerYPRR":0.4745,"careerTPRR":0.0741,"career1DRR":0.0185,"careerYACR":5.72,"careerMTF":0.16,"careerSlot":0.2424,"avgPassBlock":70.9,"avgRunBlock":64.65,"bestYPRR":0.8175,"bestTPRR":0.1176,"best1DRR":0.0365,"bestYACR":9.3,"rank":null},{"pos":"TE","name":"Farrod Green","school":"Mississippi State","conf":"SEC","cfr_id":"farrod-green-1","age":22.9068,"round":8.0,"years":4,"markers":0,"adjMarkers":-6.0,"grade":0.0,"ath":0.0,"prod":0.0,"pff":2.0,"lastPPG":4.0538,"bestPPG":4.0538,"firstYPTPA":0.2944,"lastYPTPA":0.8159,"bestYPTPA":0.8159,"bestMSYards":0.1102,"careerYPG":12.4118,"careerYPRR":0.903,"careerTPRR":0.1241,"career1DRR":0.0456,"careerYACR":7.75,"careerMTF":0.0962,"careerSlot":0.4205,"avgPassBlock":60.125,"avgRunBlock":61.5,"bestYPRR":1.1174,"bestTPRR":0.1709,"best1DRR":0.0652,"bestYACR":13.3333,"rank":null},{"pos":"TE","name":"Reggie Gilliam","school":"Toledo","conf":"MAC","cfr_id":"reggie-gilliam-1","pfr_id":"GillRe00","age":22.7123,"round":8.0,"years":3,"markers":0,"adjMarkers":-6.0,"grade":0.0,"ath":0.0,"prod":0.0,"pff":2.0,"lastPPG":1.1833,"bestPPG":2.3923,"firstYPTPA":0.0709,"lastYPTPA":0.1534,"bestYPTPA":0.1797,"bestMSYards":0.0234,"careerYPG":3.9231,"careerYPRR":0.5504,"careerTPRR":0.1079,"career1DRR":0.0288,"careerYACR":4.5556,"careerMTF":0.3889,"careerSlot":0.228,"avgPassBlock":50.7333,"avgRunBlock":69.1,"bestYPRR":0.6827,"bestTPRR":0.1376,"best1DRR":0.0385,"bestYACR":4.8889,"rank":null},{"pos":"TE","name":"Parker Houston","school":"San Diego State","conf":"MWC","cfr_id":"parker-houston-1","age":22.4164,"round":8.0,"years":4,"markers":0,"adjMarkers":-6.0,"grade":0.0,"ath":0.0,"prod":0.0,"pff":1.0,"lastPPG":2.5692,"bestPPG":3.5231,"firstYPTPA":0.126,"lastYPTPA":0.3899,"bestYPTPA":0.5705,"bestMSYards":0.0732,"careerYPG":8.5714,"careerYPRR":0.83,"careerTPRR":0.1245,"career1DRR":0.0435,"careerYACR":4.8667,"careerMTF":0.0667,"careerSlot":0.1899,"avgPassBlock":66.275,"avgRunBlock":64.15,"bestYPRR":1.2174,"bestTPRR":0.1957,"best1DRR":0.0652,"bestYACR":7.3333,"rank":null},{"pos":"TE","name":"Noah Togiai","school":"Oregon State","conf":"Pac-12","cfr_id":"noah-togiai-1","pfr_id":"TogiNo00","age":22.8356,"round":8.0,"years":5,"markers":0,"adjMarkers":-6.0,"grade":0.0,"ath":0.0,"prod":0.0,"pff":0.0,"lastPPG":8.55,"bestPPG":8.55,"boy15":3.0,"firstYPTPA":0.2135,"lastYPTPA":0.969,"bestYPTPA":1.277,"bestMSYards":0.1958,"careerYPG":23.8182,"careerYPRR":1.0215,"careerTPRR":0.1533,"career1DRR":0.0518,"careerYACR":3.7647,"careerMTF":0.0686,"careerSlot":0.4318,"avgPassBlock":64.42,"avgRunBlock":57.28,"bestYPRR":1.4871,"bestTPRR":0.184,"best1DRR":0.0909,"bestYACR":4.0294,"rank":null},{"pos":"TE","name":"Colin Thompson","school":"Temple","conf":"American","age":26.3945,"round":8.0,"markers":0,"adjMarkers":-6.0,"grade":0.0,"ath":0.0,"prod":0.0,"rank":null}]